{"timestamp": 1758960110, "current": [{"success": true, "error": null, "response": {"id": "SADM", "dataSource": "METAR_NOAA", "loc": {"long": -58.633333333333, "lat": -34.666666666667}, "place": {"name": "buenos aires/mor", "city": "buenos aires/mor", "state": "", "country": "ar"}, "profile": {"tz": "America/Argentina/Buenos_Aires", "tzname": "-03", "tzoffset": -10800, "isDST": false, "elevM": 30, "elevFT": 98}, "obTimestamp": 1758956400, "obDateTime": "2025-09-27T04:00:00-03:00", "ob": {"type": "station", "timestamp": 1758956400, "dateTimeISO": "2025-09-27T04:00:00-03:00", "recTimestamp": 1758956952, "recDateTimeISO": "2025-09-27T04:09:12-03:00", "tempC": 16, "tempF": 61, "dewpointC": 13, "dewpointF": 55, "humidity": 82, "pressureMB": 1010, "pressureIN": 29.82, "spressureMB": 1006, "spressureIN": 29.71, "altimeterMB": 1010, "altimeterIN": 29.82, "windKTS": 7, "windKPH": 13, "windMPH": 8, "windMPS": 3.6, "windSpeedKTS": 7, "windSpeedKPH": 13, "windSpeedMPH": 8, "windSpeedMPS": 3.6, "windDirDEG": 90, "windDir": "E", "windGustKTS": null, "windGustKPH": null, "windGustMPH": null, "windGustMPS": null, "flightRule": "MVFR", "visibilityKM": 7.99843968, "visibilityMI": 4.97, "weather": "Cloudy with Light Rain", "weatherShort": "Light Rain", "weatherCoded": ":L:R,::OV", "weatherPrimary": "Light Rain", "weatherPrimaryCoded": ":L:R", "cloudsCoded": "OV", "icon": "rainn.png", "heatindexC": 16.1, "heatindexF": 61, "windchillC": 16.1, "windchillF": 61, "feelslikeC": 16.1, "feelslikeF": 61, "isDay": false, "sunrise": 1758965757, "sunriseISO": "2025-09-27T06:35:57-03:00", "sunset": 1759010087, "sunsetISO": "2025-09-27T18:54:47-03:00", "snowDepthCM": null, "snowDepthIN": null, "precipMM": 0, "precipIN": 0, "solradWM2": 0, "solradMethod": "estimated", "ceilingFT": 5700, "ceilingM": 1737.36, "light": 0, "uvi": null, "QC": "O", "QCcode": 10, "trustFactor": 100, "sky": 100}, "raw": "METAR METAR SADM 270700Z 09007KT 8000 -RA SCT018 OVC057 16/13 Q1010", "relativeTo": {"lat": -34.682473965673, "long": -59.033162742123, "bearing": 87, "bearingENG": "E", "distanceKM": 36.605, "distanceMI": 22.745}}}], "forecast_24hr": [{"success": true, "error": null, "response": [{"loc": {"long": -59.033, "lat": -34.682}, "interval": "day", "place": {"name": "lujan", "state": "df", "country": "ar"}, "periods": [{"timestamp": 1758967200, "validTime": "2025-09-27T07:00:00-03:00", "dateTimeISO": "2025-09-27T07:00:00-03:00", "maxTempC": 17.5, "maxTempF": 63, "minTempC": 8.5, "minTempF": 47, "avgTempC": 13, "avgTempF": 55, "tempC": null, "tempF": null, "wetBulbGlobeTempC": 13.6, "wetBulbGlobeTempF": 57, "maxFeelslikeC": 17.5, "maxFeelslikeF": 63, "minFeelslikeC": 14.1, "minFeelslikeF": 57, "avgFeelslikeC": 15.8, "avgFeelslikeF": 60, "feelslikeC": 14.1, "feelslikeF": 57, "maxDewpointC": 14, "maxDewpointF": 57, "minDewpointC": 10, "minDewpointF": 50, "avgDewpointC": 12.3, "avgDewpointF": 54, "dewpointC": 12.8, "dewpointF": 55, "maxHumidity": 93, "minHumidity": 67, "humidity": 92, "pop": 70, "precipMM": 4.7, "precipIN": 0.18, "iceaccum": null, "iceaccumMM": null, "iceaccumIN": null, "snowCM": 0, "snowIN": 0, "pressureMB": 1008, "pressureIN": 29.77, "windDir": "ENE", "windDirDEG": 59, "windSpeedKTS": 14, "windSpeedKPH": 27, "windSpeedMPH": 17, "windSpeedMPS": 7, "windGustKTS": 33, "windGustKPH": 62, "windGustMPH": 38, "windGustMPS": 17, "windDirMax": "SW", "windDirMaxDEG": 225, "windSpeedMaxKTS": 18, "windSpeedMaxKPH": 33, "windSpeedMaxMPH": 20, "windSpeedMaxMPS": 9, "windDirMin": "NNE", "windDirMinDEG": 23, "windSpeedMinKTS": 5, "windSpeedMinKPH": 9, "windSpeedMinMPH": 6, "windSpeedMinMPS": 3, "windDir80m": "NE", "windDir80mDEG": 49, "windSpeed80mKTS": 20, "windSpeed80mKPH": 37, "windSpeed80mMPH": 23, "windSpeed80mMPS": 10, "windGust80mKTS": 27, "windGust80mKPH": 50, "windGust80mMPH": 31, "windGust80mMPS": 14, "windDirMax80m": "WSW", "windDirMax80mDEG": 241, "windSpeedMax80mKTS": 27, "windSpeedMax80mKPH": 50, "windSpeedMax80mMPH": 31, "windSpeedMax80mMPS": 14, "windDirMin80m": "W", "windDirMin80mDEG": 280, "windSpeedMin80mKTS": 18, "windSpeedMin80mKPH": 33, "windSpeedMin80mMPH": 21, "windSpeedMin80mMPS": 9, "sky": 88, "cloudsCoded": "BK", "weather": "Mostly Cloudy with Showers", "weatherCoded": [{"timestamp": 1758967200, "wx": "L::R", "dateTimeISO": "2025-09-27T07:00:00-03:00"}, {"timestamp": 1758970800, "wx": ":VL:RW", "dateTimeISO": "2025-09-27T08:00:00-03:00"}], "weatherPrimary": "Showers", "weatherPrimaryCoded": "L::R", "icon": "mcloudyr.png", "visibilityKM": 12.955, "visibilityMI": 8.05, "uvi": 5, "solradWM2": 2082.0121, "solradMinWM2": 4.0325, "solradMaxWM2": 348.0424, "isDay": true, "ghi": 16.1, "solradClearSkyWM2": 6174.2, "solradClearSkySource": "v2", "maxCoverage": "L", "sunrise": 1758965853, "sunset": 1759010183, "sunriseISO": "2025-09-27T06:37:33-03:00", "sunsetISO": "2025-09-27T18:56:23-03:00"}, {"timestamp": 1759053600, "validTime": "2025-09-28T07:00:00-03:00", "dateTimeISO": "2025-09-28T07:00:00-03:00", "maxTempC": 20.5, "maxTempF": 69, "minTempC": 9.4, "minTempF": 49, "avgTempC": 14.9, "avgTempF": 59, "tempC": null, "tempF": null, "wetBulbGlobeTempC": 10.1, "wetBulbGlobeTempF": 50, "maxFeelslikeC": 20.5, "maxFeelslikeF": 69, "minFeelslikeC": 10.2, "minFeelslikeF": 50, "avgFeelslikeC": 15.4, "avgFeelslikeF": 60, "feelslikeC": 10.2, "feelslikeF": 50, "maxDewpointC": 13.2, "maxDewpointF": 56, "minDewpointC": 5.8, "minDewpointF": 42, "avgDewpointC": 9.7, "avgDewpointF": 50, "dewpointC": 5.8, "dewpointF": 42, "maxHumidity": 74, "minHumidity": 52, "humidity": 74, "pop": 0, "precipMM": 0, "precipIN": 0, "iceaccum": null, "iceaccumMM": null, "iceaccumIN": null, "snowCM": 0, "snowIN": 0, "pressureMB": 1015, "pressureIN": 29.98, "windDir": "W", "windDirDEG": 260, "windSpeedKTS": 5, "windSpeedKPH": 9, "windSpeedMPH": 6, "windSpeedMPS": 3, "windGustKTS": 15, "windGustKPH": 27, "windGustMPH": 17, "windGustMPS": 8, "windDirMax": "W", "windDirMaxDEG": 277, "windSpeedMaxKTS": 6, "windSpeedMaxKPH": 11, "windSpeedMaxMPH": 7, "windSpeedMaxMPS": 3, "windDirMin": "NW", "windDirMinDEG": 321, "windSpeedMinKTS": 3, "windSpeedMinKPH": 5, "windSpeedMinMPH": 3, "windSpeedMinMPS": 2, "windDir80m": "WSW", "windDir80mDEG": 258, "windSpeed80mKTS": 7, "windSpeed80mKPH": 13, "windSpeed80mMPH": 8, "windSpeed80mMPS": 4, "windGust80mKTS": 10, "windGust80mKPH": 18, "windGust80mMPH": 11, "windGust80mMPS": 5, "windDirMax80m": "WNW", "windDirMax80mDEG": 297, "windSpeedMax80mKTS": 10, "windSpeedMax80mKPH": 18, "windSpeedMax80mMPH": 11, "windSpeedMax80mMPS": 5, "windDirMin80m": "W", "windDirMin80mDEG": 268, "windSpeedMin80mKTS": 6, "windSpeedMin80mKPH": 11, "windSpeedMin80mMPH": 7, "windSpeedMin80mMPS": 3, "sky": 0, "cloudsCoded": "CL", "weather": "Sunny", "weatherCoded": [], "weatherPrimary": "Sunny", "weatherPrimaryCoded": "::CL", "icon": "sunny.png", "visibilityKM": 16, "visibilityMI": 9.94, "uvi": 7, "solradWM2": 6225.08, "solradMinWM2": 18.78, "solradMaxWM2": 856.17, "isDay": true, "ghi": 18.8, "solradClearSkyWM2": 6225.08, "solradClearSkySource": "v2", "maxCoverage": "", "sunrise": 1759052168, "sunset": 1759096628, "sunriseISO": "2025-09-28T06:36:08-03:00", "sunsetISO": "2025-09-28T18:57:08-03:00"}, {"timestamp": 1759140000, "validTime": "2025-09-29T07:00:00-03:00", "dateTimeISO": "2025-09-29T07:00:00-03:00", "maxTempC": 22.9, "maxTempF": 73, "minTempC": 11.2, "minTempF": 52, "avgTempC": 17.1, "avgTempF": 63, "tempC": null, "tempF": null, "wetBulbGlobeTempC": 10.6, "wetBulbGlobeTempF": 51, "maxFeelslikeC": 22.9, "maxFeelslikeF": 73, "minFeelslikeC": 11.6, "minFeelslikeF": 53, "avgFeelslikeC": 17.2, "avgFeelslikeF": 63, "feelslikeC": 11.6, "feelslikeF": 53, "maxDewpointC": 14.4, "maxDewpointF": 58, "minDewpointC": 7.5, "minDewpointF": 46, "avgDewpointC": 11.3, "avgDewpointF": 52, "dewpointC": 7.5, "dewpointF": 46, "maxHumidity": 76, "minHumidity": 48, "humidity": 76, "pop": 0, "precipMM": 0, "precipIN": 0, "iceaccum": null, "iceaccumMM": null, "iceaccumIN": null, "snowCM": 0, "snowIN": 0, "pressureMB": 1016, "pressureIN": 30, "windDir": "NNE", "windDirDEG": 21, "windSpeedKTS": 4, "windSpeedKPH": 7, "windSpeedMPH": 4, "windSpeedMPS": 2, "windGustKTS": 15, "windGustKPH": 27, "windGustMPH": 17, "windGustMPS": 8, "windDirMax": "N", "windDirMaxDEG": 354, "windSpeedMaxKTS": 6, "windSpeedMaxKPH": 11, "windSpeedMaxMPH": 7, "windSpeedMaxMPS": 3, "windDirMin": "NNE", "windDirMinDEG": 27, "windSpeedMinKTS": 1, "windSpeedMinKPH": 2, "windSpeedMinMPH": 1, "windSpeedMinMPS": 1, "windDir80m": "NNE", "windDir80mDEG": 16, "windSpeed80mKTS": 11, "windSpeed80mKPH": 20, "windSpeed80mMPH": 12, "windSpeed80mMPS": 6, "windGust80mKTS": 11, "windGust80mKPH": 20, "windGust80mMPH": 12, "windGust80mMPS": 6, "windDirMax80m": "NNE", "windDirMax80mDEG": 16, "windSpeedMax80mKTS": 11, "windSpeedMax80mKPH": 20, "windSpeedMax80mMPH": 12, "windSpeedMax80mMPS": 6, "windDirMin80m": "N", "windDirMin80mDEG": 10, "windSpeedMin80mKTS": 4, "windSpeedMin80mKPH": 8, "windSpeedMin80mMPH": 5, "windSpeedMin80mMPS": 2, "sky": 52, "cloudsCoded": "SC", "weather": "Partly Cloudy", "weatherCoded": [], "weatherPrimary": "Partly Cloudy", "weatherPrimaryCoded": "::SC", "icon": "pcloudy.png", "visibilityKM": 16, "visibilityMI": 9.94, "uvi": 7, "solradWM2": 5135.7096, "solradMinWM2": 21.046, "solradMaxWM2": 842.6697, "isDay": true, "ghi": 21.6, "solradClearSkyWM2": 6275.81, "solradClearSkySource": "v2", "maxCoverage": "", "sunrise": 1759138483, "sunset": 1759183073, "sunriseISO": "2025-09-29T06:34:43-03:00", "sunsetISO": "2025-09-29T18:57:53-03:00"}, {"timestamp": 1759226400, "validTime": "2025-09-30T07:00:00-03:00", "dateTimeISO": "2025-09-30T07:00:00-03:00", "maxTempC": 22.8, "maxTempF": 73, "minTempC": 9.2, "minTempF": 49, "avgTempC": 16, "avgTempF": 61, "tempC": null, "tempF": null, "wetBulbGlobeTempC": 12.5, "wetBulbGlobeTempF": 54, "maxFeelslikeC": 22.8, "maxFeelslikeF": 73, "minFeelslikeC": 13.5, "minFeelslikeF": 56, "avgFeelslikeC": 18.1, "avgFeelslikeF": 65, "feelslikeC": 13.5, "feelslikeF": 56, "maxDewpointC": 13.3, "maxDewpointF": 56, "minDewpointC": 9.3, "minDewpointF": 49, "avgDewpointC": 11.1, "avgDewpointF": 52, "dewpointC": 10.3, "dewpointF": 51, "maxHumidity": 81, "minHumidity": 43, "humidity": 81, "pop": 0, "precipMM": 0, "precipIN": 0, "iceaccum": null, "iceaccumMM": null, "iceaccumIN": null, "snowCM": 0, "snowIN": 0, "pressureMB": 1022, "pressureIN": 30.18, "windDir": "SSW", "windDirDEG": 197, "windSpeedKTS": 3, "windSpeedKPH": 6, "windSpeedMPH": 3, "windSpeedMPS": 2, "windGustKTS": 21, "windGustKPH": 40, "windGustMPH": 25, "windGustMPS": 11, "windDirMax": "S", "windDirMaxDEG": 170, "windSpeedMaxKTS": 12, "windSpeedMaxKPH": 22, "windSpeedMaxMPH": 13, "windSpeedMaxMPS": 6, "windDirMin": "SSW", "windDirMinDEG": 197, "windSpeedMinKTS": 3, "windSpeedMinKPH": 6, "windSpeedMinMPH": 3, "windSpeedMinMPS": 2, "windDir80m": "S", "windDir80mDEG": 174, "windSpeed80mKTS": 13, "windSpeed80mKPH": 23, "windSpeed80mMPH": 15, "windSpeed80mMPS": 7, "windGust80mKTS": 17, "windGust80mKPH": 31, "windGust80mMPH": 19, "windGust80mMPS": 9, "windDirMax80m": "S", "windDirMax80mDEG": 169, "windSpeedMax80mKTS": 17, "windSpeedMax80mKPH": 31, "windSpeedMax80mMPH": 19, "windSpeedMax80mMPS": 9, "windDirMin80m": "S", "windDirMin80mDEG": 175, "windSpeedMin80mKTS": 11, "windSpeedMin80mKPH": 20, "windSpeedMin80mMPH": 12, "windSpeedMin80mMPS": 6, "sky": 67, "cloudsCoded": "SC", "weather": "Partly Cloudy", "weatherCoded": [], "weatherPrimary": "Partly Cloudy", "weatherPrimaryCoded": "::SC", "icon": "pcloudy.png", "visibilityKM": 16, "visibilityMI": 9.94, "uvi": 7, "solradWM2": 3602.7232, "solradMinWM2": 24.3453, "solradMaxWM2": 716.3565, "isDay": true, "ghi": 24.6, "solradClearSkyWM2": 6326.37, "solradClearSkySource": "v2", "maxCoverage": "", "sunrise": 1759224798, "sunset": 1759269518, "sunriseISO": "2025-09-30T06:33:18-03:00", "sunsetISO": "2025-09-30T18:58:38-03:00"}, {"timestamp": 1759312800, "validTime": "2025-10-01T07:00:00-03:00", "dateTimeISO": "2025-10-01T07:00:00-03:00", "maxTempC": 21.6, "maxTempF": 71, "minTempC": 10.3, "minTempF": 51, "avgTempC": 15.9, "avgTempF": 61, "tempC": null, "tempF": null, "wetBulbGlobeTempC": 10.6, "wetBulbGlobeTempF": 51, "maxFeelslikeC": 21.6, "maxFeelslikeF": 71, "minFeelslikeC": 11.4, "minFeelslikeF": 53, "avgFeelslikeC": 16.5, "avgFeelslikeF": 62, "feelslikeC": 11.4, "feelslikeF": 53, "maxDewpointC": 9.8, "maxDewpointF": 50, "minDewpointC": 5.6, "minDewpointF": 42, "avgDewpointC": 7.9, "avgDewpointF": 46, "dewpointC": 5.6, "dewpointF": 42, "maxHumidity": 67, "minHumidity": 38, "humidity": 67, "pop": 0, "precipMM": 0, "precipIN": 0, "iceaccum": null, "iceaccumMM": null, "iceaccumIN": null, "snowCM": 0, "snowIN": 0, "pressureMB": 1026, "pressureIN": 30.31, "windDir": "ESE", "windDirDEG": 108, "windSpeedKTS": 5, "windSpeedKPH": 9, "windSpeedMPH": 5, "windSpeedMPS": 2, "windGustKTS": 11, "windGustKPH": 20, "windGustMPH": 13, "windGustMPS": 6, "windDirMax": "ENE", "windDirMaxDEG": 63, "windSpeedMaxKTS": 6, "windSpeedMaxKPH": 11, "windSpeedMaxMPH": 7, "windSpeedMaxMPS": 3, "windDirMin": "NE", "windDirMinDEG": 45, "windSpeedMinKTS": 4, "windSpeedMinKPH": 7, "windSpeedMinMPH": 4, "windSpeedMinMPS": 2, "windDir80m": "E", "windDir80mDEG": 93, "windSpeed80mKTS": 10, "windSpeed80mKPH": 18, "windSpeed80mMPH": 11, "windSpeed80mMPS": 5, "windGust80mKTS": 10, "windGust80mKPH": 18, "windGust80mMPH": 11, "windGust80mMPS": 5, "windDirMax80m": "E", "windDirMax80mDEG": 93, "windSpeedMax80mKTS": 10, "windSpeedMax80mKPH": 18, "windSpeedMax80mMPH": 11, "windSpeedMax80mMPS": 5, "windDirMin80m": "NE", "windDirMin80mDEG": 43, "windSpeedMin80mKTS": 5, "windSpeedMin80mKPH": 9, "windSpeedMin80mMPH": 6, "windSpeedMin80mMPS": 3, "sky": 75, "cloudsCoded": "BK", "weather": "Mostly Cloudy", "weatherCoded": [], "weatherPrimary": "Mostly Cloudy", "weatherPrimaryCoded": "::BK", "icon": "mcloudy.png", "visibilityKM": 16, "visibilityMI": 9.94, "uvi": 1, "solradWM2": 3793.4965, "solradMinWM2": 26.3778, "solradMaxWM2": 852.2346, "isDay": true, "ghi": 27.7, "solradClearSkyWM2": 6376.75, "solradClearSkySource": "v2", "maxCoverage": "", "sunrise": 1759311114, "sunset": 1759355963, "sunriseISO": "2025-10-01T06:31:54-03:00", "sunsetISO": "2025-10-01T18:59:23-03:00"}, {"timestamp": 1759399200, "validTime": "2025-10-02T07:00:00-03:00", "dateTimeISO": "2025-10-02T07:00:00-03:00", "maxTempC": 23.9, "maxTempF": 75, "minTempC": 14.1, "minTempF": 57, "avgTempC": 19, "avgTempF": 66, "tempC": null, "tempF": null, "wetBulbGlobeTempC": 11.6, "wetBulbGlobeTempF": 53, "maxFeelslikeC": 23.9, "maxFeelslikeF": 75, "minFeelslikeC": 12.4, "minFeelslikeF": 54, "avgFeelslikeC": 18.1, "avgFeelslikeF": 65, "feelslikeC": 12.4, "feelslikeF": 54, "maxDewpointC": 12, "maxDewpointF": 54, "minDewpointC": 9, "minDewpointF": 48, "avgDewpointC": 10.3, "avgDewpointF": 51, "dewpointC": 9.8, "dewpointF": 50, "maxHumidity": 85, "minHumidity": 39, "humidity": 85, "pop": 0, "precipMM": 0, "precipIN": 0, "iceaccum": null, "iceaccumMM": null, "iceaccumIN": null, "snowCM": 0, "snowIN": 0, "pressureMB": 1022, "pressureIN": 30.17, "windDir": "NNE", "windDirDEG": 33, "windSpeedKTS": 5, "windSpeedKPH": 8, "windSpeedMPH": 5, "windSpeedMPS": 2, "windGustKTS": 8, "windGustKPH": 14, "windGustMPH": 9, "windGustMPS": 4, "windDirMax": "NNE", "windDirMaxDEG": 29, "windSpeedMaxKTS": 6, "windSpeedMaxKPH": 11, "windSpeedMaxMPH": 7, "windSpeedMaxMPS": 3, "windDirMin": "N", "windDirMinDEG": 8, "windSpeedMinKTS": 4, "windSpeedMinKPH": 7, "windSpeedMinMPH": 4, "windSpeedMinMPS": 2, "windDir80m": "NNE", "windDir80mDEG": 28, "windSpeed80mKTS": 9, "windSpeed80mKPH": 17, "windSpeed80mMPH": 11, "windSpeed80mMPS": 5, "windGust80mKTS": 9, "windGust80mKPH": 17, "windGust80mMPH": 11, "windGust80mMPS": 5, "windDirMax80m": "NNE", "windDirMax80mDEG": 28, "windSpeedMax80mKTS": 9, "windSpeedMax80mKPH": 17, "windSpeedMax80mMPH": 11, "windSpeedMax80mMPS": 5, "windDirMin80m": "NE", "windDirMin80mDEG": 43, "windSpeedMin80mKTS": 5, "windSpeedMin80mKPH": 9, "windSpeedMin80mMPH": 6, "windSpeedMin80mMPS": 3, "sky": 4, "cloudsCoded": "CL", "weather": "Sunny", "weatherCoded": [], "weatherPrimary": "Sunny", "weatherPrimaryCoded": "::CL", "icon": "sunny.png", "visibilityKM": 16, "visibilityMI": 9.94, "uvi": null, "solradWM2": 6426.7252, "solradMinWM2": 30.9178, "solradMaxWM2": 873.9132, "isDay": true, "ghi": 30.9, "solradClearSkyWM2": 6426.9, "solradClearSkySource": "v2", "maxCoverage": "", "sunrise": 1759397430, "sunset": 1759442409, "sunriseISO": "2025-10-02T06:30:30-03:00", "sunsetISO": "2025-10-02T19:00:09-03:00"}, {"timestamp": 1759485600, "validTime": "2025-10-03T07:00:00-03:00", "dateTimeISO": "2025-10-03T07:00:00-03:00", "maxTempC": 25.1, "maxTempF": 77, "minTempC": 18.6, "minTempF": 65, "avgTempC": 21.9, "avgTempF": 71, "tempC": null, "tempF": null, "wetBulbGlobeTempC": 13.9, "wetBulbGlobeTempF": 57, "maxFeelslikeC": 25.1, "maxFeelslikeF": 77, "minFeelslikeC": 16.3, "minFeelslikeF": 61, "avgFeelslikeC": 20.7, "avgFeelslikeF": 69, "feelslikeC": 16.3, "feelslikeF": 61, "maxDewpointC": 14.2, "maxDewpointF": 58, "minDewpointC": 9.4, "minDewpointF": 49, "avgDewpointC": 11.9, "avgDewpointF": 53, "dewpointC": 9.4, "dewpointF": 49, "maxHumidity": 66, "minHumidity": 45, "humidity": 63, "pop": 0, "precipMM": 0, "precipIN": 0, "iceaccum": null, "iceaccumMM": null, "iceaccumIN": null, "snowCM": 0, "snowIN": 0, "pressureMB": 1016, "pressureIN": 29.99, "windDir": "N", "windDirDEG": 351, "windSpeedKTS": 5, "windSpeedKPH": 10, "windSpeedMPH": 6, "windSpeedMPS": 3, "windGustKTS": 9, "windGustKPH": 18, "windGustMPH": 11, "windGustMPS": 5, "windDirMax": "N", "windDirMaxDEG": 2, "windSpeedMaxKTS": 6, "windSpeedMaxKPH": 11, "windSpeedMaxMPH": 7, "windSpeedMaxMPS": 3, "windDirMin": "W", "windDirMinDEG": 277, "windSpeedMinKTS": 1, "windSpeedMinKPH": 2, "windSpeedMinMPH": 1, "windSpeedMinMPS": 0, "windDir80m": "N", "windDir80mDEG": 356, "windSpeed80mKTS": 8, "windSpeed80mKPH": 14, "windSpeed80mMPH": 9, "windSpeed80mMPS": 4, "windGust80mKTS": 8, "windGust80mKPH": 14, "windGust80mMPH": 9, "windGust80mMPS": 4, "windDirMax80m": "N", "windDirMax80mDEG": 356, "windSpeedMax80mKTS": 8, "windSpeedMax80mKPH": 14, "windSpeedMax80mMPH": 9, "windSpeedMax80mMPS": 4, "windDirMin80m": "WNW", "windDirMin80mDEG": 293, "windSpeedMin80mKTS": 1, "windSpeedMin80mKPH": 2, "windSpeedMin80mMPH": 1, "windSpeedMin80mMPS": 1, "sky": 48, "cloudsCoded": "SC", "weather": "Partly Cloudy", "weatherCoded": [], "weatherPrimary": "Partly Cloudy", "weatherPrimaryCoded": "::SC", "icon": "pcloudy.png", "visibilityKM": 16, "visibilityMI": 9.94, "uvi": null, "solradWM2": 5712.0529, "solradMinWM2": 32.6825, "solradMaxWM2": 877.9739, "isDay": true, "ghi": 34.3, "solradClearSkyWM2": 6476.84, "solradClearSkySource": "v2", "maxCoverage": "", "sunrise": 1759483747, "sunset": 1759528855, "sunriseISO": "2025-10-03T06:29:07-03:00", "sunsetISO": "2025-10-03T19:00:55-03:00"}], "profile": {"tz": "America/Argentina/Buenos_Aires", "elevM": 17, "elevFT": 56}}]}], "forecast_3hr": [{"success": true, "error": null, "response": [{"loc": {"long": -59.033, "lat": -34.682}, "interval": "3hr", "place": {"name": "lujan", "state": "df", "country": "ar"}, "periods": [{"timestamp": 1758963600, "validTime": "2025-09-27T06:00:00-03:00", "dateTimeISO": "2025-09-27T06:00:00-03:00", "maxTempC": 14.2, "maxTempF": 58, "minTempC": 14.1, "minTempF": 57, "avgTempC": 14.1, "avgTempF": 57, "tempC": 14.1, "tempF": 57, "wetBulbGlobeTempC": 13.5, "wetBulbGlobeTempF": 56, "maxFeelslikeC": 14.2, "maxFeelslikeF": 58, "minFeelslikeC": 14.1, "minFeelslikeF": 57, "avgFeelslikeC": 14.2, "avgFeelslikeF": 57, "feelslikeC": 14.1, "feelslikeF": 57, "maxDewpointC": 13.1, "maxDewpointF": 56, "minDewpointC": 12.7, "minDewpointF": 55, "avgDewpointC": 12.8, "avgDewpointF": 55, "dewpointC": 12.7, "dewpointF": 55, "maxHumidity": 93, "minHumidity": 91, "humidity": 91, "pop": 100, "precipMM": 6.6, "precipIN": 0.26, "iceaccum": null, "iceaccumMM": null, "iceaccumIN": null, "snowCM": 0, "snowIN": 0, "pressureMB": 1009, "pressureIN": 29.78, "windDir": "ENE", "windDirDEG": 60, "windSpeedKTS": 10, "windSpeedKPH": 19, "windSpeedMPH": 12, "windSpeedMPS": 5, "windGustKTS": 27, "windGustKPH": 50, "windGustMPH": 31, "windGustMPS": 14, "windDirMax": "ENE", "windDirMaxDEG": 59, "windSpeedMaxKTS": 14, "windSpeedMaxKPH": 27, "windSpeedMaxMPH": 17, "windSpeedMaxMPS": 7, "windDirMin": "ENE", "windDirMinDEG": 60, "windSpeedMinKTS": 10, "windSpeedMinKPH": 19, "windSpeedMinMPH": 12, "windSpeedMinMPS": 5, "windDir80m": "NE", "windDir80mDEG": 38, "windSpeed80mKTS": 16, "windSpeed80mKPH": 29, "windSpeed80mMPH": 18, "windSpeed80mMPS": 8, "windGust80mKTS": 23, "windGust80mKPH": 43, "windGust80mMPH": 27, "windGust80mMPS": 12, "windDirMax80m": "NNE", "windDirMax80mDEG": 29, "windSpeedMax80mKTS": 23, "windSpeedMax80mKPH": 43, "windSpeedMax80mMPH": 27, "windSpeedMax80mMPS": 12, "windDirMin80m": "NE", "windDirMin80mDEG": 38, "windSpeedMin80mKTS": 16, "windSpeedMin80mKPH": 29, "windSpeedMin80mMPH": 18, "windSpeedMin80mMPS": 8, "sky": 100, "cloudsCoded": "OV", "weather": "Cloudy with Rain Likely", "weatherCoded": [{"timestamp": 1758963600, "wx": "L::R", "dateTimeISO": "2025-09-27T06:00:00-03:00"}, {"timestamp": 1758970800, "wx": ":VL:RW", "dateTimeISO": "2025-09-27T08:00:00-03:00"}], "weatherPrimary": "Rain", "weatherPrimaryCoded": "L::R", "icon": "rainn.png", "visibilityKM": 7.5522, "visibilityMI": 4.69, "uvi": 0, "solradWM2": 56, "solradMinWM2": 0, "solradMaxWM2": 51.6925, "isDay": false, "ghi": 0, "solrad": {"azimuthDEG": 98.1707, "zenithDEG": 98.8167, "ghiWM2": 55.725, "dniWM2": 0, "dhiWM2": 55.725, "version": "v2"}, "solradClearSkyWM2": 222.9, "solradClearSkySource": "v2", "maxCoverage": "L", "spressureMB": 1007, "spressureIN": 29.72, "altimeterMB": 1008, "altimeterIN": 29.78}, {"timestamp": 1758974400, "validTime": "2025-09-27T09:00:00-03:00", "dateTimeISO": "2025-09-27T09:00:00-03:00", "maxTempC": 16.4, "maxTempF": 61, "minTempC": 14.3, "minTempF": 58, "avgTempC": 15.3, "avgTempF": 60, "tempC": 14.3, "tempF": 58, "wetBulbGlobeTempC": 14.2, "wetBulbGlobeTempF": 58, "maxFeelslikeC": 16.4, "maxFeelslikeF": 61, "minFeelslikeC": 14.3, "minFeelslikeF": 58, "avgFeelslikeC": 15.3, "avgFeelslikeF": 60, "feelslikeC": 14.3, "feelslikeF": 58, "maxDewpointC": 14, "maxDewpointF": 57, "minDewpointC": 12, "minDewpointF": 54, "avgDewpointC": 13, "avgDewpointF": 55, "dewpointC": 13.1, "dewpointF": 56, "maxHumidity": 93, "minHumidity": 75, "humidity": 93, "pop": 10, "precipMM": 0.3, "precipIN": 0.01, "iceaccum": null, "iceaccumMM": null, "iceaccumIN": null, "snowCM": 0, "snowIN": 0, "pressureMB": 1007, "pressureIN": 29.74, "windDir": "NE", "windDirDEG": 42, "windSpeedKTS": 12, "windSpeedKPH": 23, "windSpeedMPH": 14, "windSpeedMPS": 6, "windGustKTS": 23, "windGustKPH": 43, "windGustMPH": 27, "windGustMPS": 12, "windDirMax": "NE", "windDirMaxDEG": 42, "windSpeedMaxKTS": 12, "windSpeedMaxKPH": 23, "windSpeedMaxMPH": 14, "windSpeedMaxMPS": 6, "windDirMin": "NNE", "windDirMinDEG": 23, "windSpeedMinKTS": 10, "windSpeedMinKPH": 18, "windSpeedMinMPH": 11, "windSpeedMinMPS": 5, "windDir80m": "N", "windDir80mDEG": 11, "windSpeed80mKTS": 23, "windSpeed80mKPH": 43, "windSpeed80mMPH": 27, "windSpeed80mMPS": 12, "windGust80mKTS": 24, "windGust80mKPH": 44, "windGust80mMPH": 28, "windGust80mMPS": 12, "windDirMax80m": "NNW", "windDirMax80mDEG": 348, "windSpeedMax80mKTS": 24, "windSpeedMax80mKPH": 44, "windSpeedMax80mMPH": 28, "windSpeedMax80mMPS": 12, "windDirMin80m": "NW", "windDirMin80mDEG": 305, "windSpeedMin80mKTS": 22, "windSpeedMin80mKPH": 41, "windSpeedMin80mMPH": 26, "windSpeedMin80mMPS": 12, "sky": 100, "cloudsCoded": "OV", "weather": "Cloudy with Light Rain Showers", "weatherCoded": [{"timestamp": 1758974400, "wx": ":VL:RW", "dateTimeISO": "2025-09-27T09:00:00-03:00"}], "weatherPrimary": "Rain Showers", "weatherPrimaryCoded": ":VL:RW", "icon": "showers.png", "visibilityKM": 11.3265, "visibilityMI": 7.04, "uvi": 0, "solradWM2": 446, "solradMinWM2": 105.665, "solradMaxWM2": 207.9607, "isDay": true, "ghi": 422.7, "solrad": {"azimuthDEG": 71.0871, "zenithDEG": 62.2448, "ghiWM2": 445.69, "dniWM2": 845.1508, "dhiWM2": 52.1078, "version": "v2"}, "solradClearSkyWM2": 1782.76, "solradClearSkySource": "v2", "maxCoverage": "", "spressureMB": 1005, "spressureIN": 29.68, "altimeterMB": 1007, "altimeterIN": 29.73}, {"timestamp": 1758985200, "validTime": "2025-09-27T12:00:00-03:00", "dateTimeISO": "2025-09-27T12:00:00-03:00", "maxTempC": 17.5, "maxTempF": 63, "minTempC": 16.7, "minTempF": 62, "avgTempC": 17.1, "avgTempF": 63, "tempC": 17.5, "tempF": 63, "wetBulbGlobeTempC": 16.7, "wetBulbGlobeTempF": 62, "maxFeelslikeC": 17.5, "maxFeelslikeF": 63, "minFeelslikeC": 16.7, "minFeelslikeF": 62, "avgFeelslikeC": 17.1, "avgFeelslikeF": 63, "feelslikeC": 17.5, "feelslikeF": 63, "maxDewpointC": 13.3, "maxDewpointF": 56, "minDewpointC": 11.9, "minDewpointF": 53, "avgDewpointC": 12.8, "avgDewpointF": 55, "dewpointC": 13.3, "dewpointF": 56, "maxHumidity": 77, "minHumidity": 74, "humidity": 76, "pop": 10, "precipMM": 0.5, "precipIN": 0.02, "iceaccum": null, "iceaccumMM": null, "iceaccumIN": null, "snowCM": 0, "snowIN": 0, "pressureMB": 1007, "pressureIN": 29.72, "windDir": "NW", "windDirDEG": 325, "windSpeedKTS": 10, "windSpeedKPH": 18, "windSpeedMPH": 11, "windSpeedMPS": 5, "windGustKTS": 27, "windGustKPH": 49, "windGustMPH": 31, "windGustMPS": 14, "windDirMax": "WSW", "windDirMaxDEG": 250, "windSpeedMaxKTS": 15, "windSpeedMaxKPH": 28, "windSpeedMaxMPH": 17, "windSpeedMaxMPS": 8, "windDirMin": "NW", "windDirMinDEG": 325, "windSpeedMinKTS": 10, "windSpeedMinKPH": 18, "windSpeedMinMPH": 11, "windSpeedMinMPS": 5, "windDir80m": "W", "windDir80mDEG": 280, "windSpeed80mKTS": 18, "windSpeed80mKPH": 33, "windSpeed80mMPH": 21, "windSpeed80mMPS": 9, "windGust80mKTS": 27, "windGust80mKPH": 50, "windGust80mMPH": 31, "windGust80mMPS": 14, "windDirMax80m": "WSW", "windDirMax80mDEG": 241, "windSpeedMax80mKTS": 27, "windSpeedMax80mKPH": 50, "windSpeedMax80mMPH": 31, "windSpeedMax80mMPS": 14, "windDirMin80m": "W", "windDirMin80mDEG": 280, "windSpeedMin80mKTS": 18, "windSpeedMin80mKPH": 33, "windSpeedMin80mMPH": 21, "windSpeedMin80mMPS": 9, "sky": 100, "cloudsCoded": "OV", "weather": "Cloudy with Light Rain Showers", "weatherCoded": [{"timestamp": 1758985200, "wx": ":VL:RW", "dateTimeISO": "2025-09-27T12:00:00-03:00"}], "weatherPrimary": "Rain Showers", "weatherPrimaryCoded": ":VL:RW", "icon": "showers.png", "visibilityKM": 12.3768, "visibilityMI": 7.69, "uvi": 5, "solradWM2": 622, "solradMinWM2": 201.2725, "solradMaxWM2": 212.9025, "isDay": true, "ghi": 832.9, "solrad": {"azimuthDEG": 21.1295, "zenithDEG": 34.7718, "ghiWM2": 622.3975, "dniWM2": 305.0557, "dhiWM2": 371.8157, "version": "v2"}, "solradClearSkyWM2": 2489.59, "solradClearSkySource": "v2", "maxCoverage": "", "spressureMB": 1004, "spressureIN": 29.66, "altimeterMB": 1006, "altimeterIN": 29.71}, {"timestamp": 1758996000, "validTime": "2025-09-27T15:00:00-03:00", "dateTimeISO": "2025-09-27T15:00:00-03:00", "maxTempC": 16.3, "maxTempF": 61, "minTempC": 16.2, "minTempF": 61, "avgTempC": 16.2, "avgTempF": 61, "tempC": 16.3, "tempF": 61, "wetBulbGlobeTempC": 14.9, "wetBulbGlobeTempF": 59, "maxFeelslikeC": 16.3, "maxFeelslikeF": 61, "minFeelslikeC": 16.2, "minFeelslikeF": 61, "avgFeelslikeC": 16.2, "avgFeelslikeF": 61, "feelslikeC": 16.3, "feelslikeF": 61, "maxDewpointC": 11.6, "maxDewpointF": 53, "minDewpointC": 11.1, "minDewpointF": 52, "avgDewpointC": 11.3, "avgDewpointF": 52, "dewpointC": 11.4, "dewpointF": 52, "maxHumidity": 74, "minHumidity": 72, "humidity": 73, "pop": 10, "precipMM": 0.2, "precipIN": 0.01, "iceaccum": null, "iceaccumMM": null, "iceaccumIN": null, "snowCM": 0, "snowIN": 0, "pressureMB": 1010, "pressureIN": 29.81, "windDir": "SW", "windDirDEG": 234, "windSpeedKTS": 17, "windSpeedKPH": 31, "windSpeedMPH": 19, "windSpeedMPS": 9, "windGustKTS": 33, "windGustKPH": 62, "windGustMPH": 38, "windGustMPS": 17, "windDirMax": "SW", "windDirMaxDEG": 225, "windSpeedMaxKTS": 18, "windSpeedMaxKPH": 33, "windSpeedMaxMPH": 20, "windSpeedMaxMPS": 9, "windDirMin": "SW", "windDirMinDEG": 234, "windSpeedMinKTS": 17, "windSpeedMinKPH": 31, "windSpeedMinMPH": 19, "windSpeedMinMPS": 9, "windDir80m": "SW", "windDir80mDEG": 230, "windSpeed80mKTS": 25, "windSpeed80mKPH": 47, "windSpeed80mMPH": 29, "windSpeed80mMPS": 13, "windGust80mKTS": 25, "windGust80mKPH": 47, "windGust80mMPH": 29, "windGust80mMPS": 13, "windDirMax80m": "SW", "windDirMax80mDEG": 230, "windSpeedMax80mKTS": 25, "windSpeedMax80mKPH": 47, "windSpeedMax80mMPH": 29, "windSpeedMax80mMPS": 13, "windDirMin80m": "WSW", "windDirMin80mDEG": 241, "windSpeedMin80mKTS": 23, "windSpeedMin80mKPH": 43, "windSpeedMin80mMPH": 27, "windSpeedMin80mMPS": 12, "sky": 78, "cloudsCoded": "BK", "weather": "Mostly Cloudy with Showers", "weatherCoded": [{"timestamp": 1758996000, "wx": ":VL:RW", "dateTimeISO": "2025-09-27T15:00:00-03:00"}], "weatherPrimary": "Showers", "weatherPrimaryCoded": ":VL:RW", "icon": "mcloudyr.png", "visibilityKM": 16, "visibilityMI": 9.94, "uvi": 1, "solradWM2": 1060, "solradMinWM2": 174.1825, "solradMaxWM2": 348.0424, "isDay": true, "ghi": 696.7, "solrad": {"azimuthDEG": 309.527, "zenithDEG": 45.1094, "ghiWM2": 1060.0194, "dniWM2": 548.186, "dhiWM2": 673.1339, "version": "v2"}, "solradClearSkyWM2": 1564.01, "solradClearSkySource": "v2", "maxCoverage": "", "spressureMB": 1008, "spressureIN": 29.75, "altimeterMB": 1009, "altimeterIN": 29.81}, {"timestamp": 1759006800, "validTime": "2025-09-27T18:00:00-03:00", "dateTimeISO": "2025-09-27T18:00:00-03:00", "maxTempC": 16.1, "maxTempF": 61, "minTempC": 14.6, "minTempF": 58, "avgTempC": 15.3, "avgTempF": 60, "tempC": 16.1, "tempF": 61, "wetBulbGlobeTempC": 14, "wetBulbGlobeTempF": 57, "maxFeelslikeC": 16.1, "maxFeelslikeF": 61, "minFeelslikeC": 14.6, "minFeelslikeF": 58, "avgFeelslikeC": 15.3, "avgFeelslikeF": 60, "feelslikeC": 16.1, "feelslikeF": 61, "maxDewpointC": 10, "maxDewpointF": 50, "minDewpointC": 8.7, "minDewpointF": 48, "avgDewpointC": 9.2, "avgDewpointF": 49, "dewpointC": 10, "dewpointF": 50, "maxHumidity": 68, "minHumidity": 66, "humidity": 67, "pop": 0, "precipMM": 0, "precipIN": 0, "iceaccum": null, "iceaccumMM": null, "iceaccumIN": null, "snowCM": 0, "snowIN": 0, "pressureMB": 1013, "pressureIN": 29.9, "windDir": "SW", "windDirDEG": 225, "windSpeedKTS": 14, "windSpeedKPH": 25, "windSpeedMPH": 16, "windSpeedMPS": 7, "windGustKTS": 25, "windGustKPH": 45, "windGustMPH": 28, "windGustMPS": 13, "windDirMax": "SW", "windDirMaxDEG": 225, "windSpeedMaxKTS": 14, "windSpeedMaxKPH": 25, "windSpeedMaxMPH": 16, "windSpeedMaxMPS": 7, "windDirMin": "SW", "windDirMinDEG": 231, "windSpeedMinKTS": 11, "windSpeedMinKPH": 20, "windSpeedMinMPH": 12, "windSpeedMinMPS": 6, "windDir80m": "SW", "windDir80mDEG": 234, "windSpeed80mKTS": 22, "windSpeed80mKPH": 41, "windSpeed80mMPH": 26, "windSpeed80mMPS": 12, "windGust80mKTS": 22, "windGust80mKPH": 41, "windGust80mMPH": 26, "windGust80mMPS": 12, "windDirMax80m": "SW", "windDirMax80mDEG": 234, "windSpeedMax80mKTS": 22, "windSpeedMax80mKPH": 41, "windSpeedMax80mMPH": 26, "windSpeedMax80mMPS": 12, "windDirMin80m": "WSW", "windDirMin80mDEG": 240, "windSpeedMin80mKTS": 18, "windSpeedMin80mKPH": 33, "windSpeedMin80mMPH": 20, "windSpeedMin80mMPS": 9, "sky": 21, "cloudsCoded": "FW", "weather": "Mostly Sunny", "weatherCoded": [], "weatherPrimary": "Mostly Sunny", "weatherPrimaryCoded": "::FW", "icon": "fair.png", "visibilityKM": 16, "visibilityMI": 9.94, "uvi": 0, "solradWM2": 115, "solradMinWM2": 0, "solradMaxWM2": 114.6213, "isDay": true, "ghi": 114.9, "solrad": {"azimuthDEG": 275.2991, "zenithDEG": 79.2357, "ghiWM2": 114.5124, "dniWM2": 319.8938, "dhiWM2": 54.7659, "version": "v2"}, "solradClearSkyWM2": 114.94, "solradClearSkySource": "v2", "maxCoverage": "", "spressureMB": 1011, "spressureIN": 29.84, "altimeterMB": 1012, "altimeterIN": 29.9}, {"timestamp": 1759017600, "validTime": "2025-09-27T21:00:00-03:00", "dateTimeISO": "2025-09-27T21:00:00-03:00", "maxTempC": 13.8, "maxTempF": 57, "minTempC": 12.3, "minTempF": 54, "avgTempC": 13, "avgTempF": 55, "tempC": 13.8, "tempF": 57, "wetBulbGlobeTempC": 11.7, "wetBulbGlobeTempF": 53, "maxFeelslikeC": 13.8, "maxFeelslikeF": 57, "minFeelslikeC": 12.3, "minFeelslikeF": 54, "avgFeelslikeC": 13, "avgFeelslikeF": 55, "feelslikeC": 13.8, "feelslikeF": 57, "maxDewpointC": 8.4, "maxDewpointF": 47, "minDewpointC": 7.8, "minDewpointF": 46, "avgDewpointC": 8.1, "avgDewpointF": 47, "dewpointC": 8.4, "dewpointF": 47, "maxHumidity": 74, "minHumidity": 70, "humidity": 70, "pop": 0, "precipMM": 0, "precipIN": 0, "iceaccum": null, "iceaccumMM": null, "iceaccumIN": null, "snowCM": 0, "snowIN": 0, "pressureMB": 1015, "pressureIN": 29.98, "windDir": "SW", "windDirDEG": 235, "windSpeedKTS": 12, "windSpeedKPH": 22, "windSpeedMPH": 13, "windSpeedMPS": 6, "windGustKTS": 21, "windGustKPH": 39, "windGustMPH": 25, "windGustMPS": 11, "windDirMax": "SW", "windDirMaxDEG": 235, "windSpeedMaxKTS": 12, "windSpeedMaxKPH": 22, "windSpeedMaxMPH": 13, "windSpeedMaxMPS": 6, "windDirMin": "SW", "windDirMinDEG": 234, "windSpeedMinKTS": 9, "windSpeedMinKPH": 16, "windSpeedMinMPH": 10, "windSpeedMinMPS": 5, "windDir80m": "WSW", "windDir80mDEG": 242, "windSpeed80mKTS": 17, "windSpeed80mKPH": 32, "windSpeed80mMPH": 20, "windSpeed80mMPS": 9, "windGust80mKTS": 17, "windGust80mKPH": 32, "windGust80mMPH": 20, "windGust80mMPS": 9, "windDirMax80m": "WSW", "windDirMax80mDEG": 242, "windSpeedMax80mKTS": 17, "windSpeedMax80mKPH": 32, "windSpeedMax80mMPH": 20, "windSpeedMax80mMPS": 9, "windDirMin80m": "W", "windDirMin80mDEG": 270, "windSpeedMin80mKTS": 11, "windSpeedMin80mKPH": 20, "windSpeedMin80mMPH": 12, "windSpeedMin80mMPS": 6, "sky": 18, "cloudsCoded": "FW", "weather": "Mostly Clear", "weatherCoded": [], "weatherPrimary": "Mostly Clear", "weatherPrimaryCoded": "::FW", "icon": "fairn.png", "visibilityKM": 16, "visibilityMI": 9.94, "uvi": 0, "solradWM2": 0, "solradMinWM2": 0, "solradMaxWM2": 0, "isDay": false, "ghi": 0, "solrad": {"azimuthDEG": 248.0116, "zenithDEG": 115.5362, "ghiWM2": 0, "dniWM2": 0, "dhiWM2": 0, "version": "v2"}, "solradClearSkyWM2": 0, "solradClearSkySource": "v2", "maxCoverage": "", "spressureMB": 1013, "spressureIN": 29.92, "altimeterMB": 1015, "altimeterIN": 29.97}, {"timestamp": 1759028400, "validTime": "2025-09-28T00:00:00-03:00", "dateTimeISO": "2025-09-28T00:00:00-03:00", "maxTempC": 11.5, "maxTempF": 53, "minTempC": 10.6, "minTempF": 51, "avgTempC": 11.1, "avgTempF": 52, "tempC": 11.5, "tempF": 53, "wetBulbGlobeTempC": 10.5, "wetBulbGlobeTempF": 51, "maxFeelslikeC": 11.5, "maxFeelslikeF": 53, "minFeelslikeC": 10.6, "minFeelslikeF": 51, "avgFeelslikeC": 11.1, "avgFeelslikeF": 52, "feelslikeC": 11.5, "feelslikeF": 53, "maxDewpointC": 7.5, "maxDewpointF": 45, "minDewpointC": 6.9, "minDewpointF": 44, "avgDewpointC": 7.2, "avgDewpointF": 45, "dewpointC": 7.5, "dewpointF": 45, "maxHumidity": 78, "minHumidity": 76, "humidity": 76, "pop": 0, "precipMM": 0, "precipIN": 0, "iceaccum": null, "iceaccumMM": null, "iceaccumIN": null, "snowCM": 0, "snowIN": 0, "pressureMB": 1016, "pressureIN": 29.99, "windDir": "WSW", "windDirDEG": 244, "windSpeedKTS": 7, "windSpeedKPH": 13, "windSpeedMPH": 8, "windSpeedMPS": 4, "windGustKTS": 13, "windGustKPH": 23, "windGustMPH": 15, "windGustMPS": 7, "windDirMax": "WSW", "windDirMaxDEG": 244, "windSpeedMaxKTS": 7, "windSpeedMaxKPH": 13, "windSpeedMaxMPH": 8, "windSpeedMaxMPS": 4, "windDirMin": "WSW", "windDirMinDEG": 251, "windSpeedMinKTS": 6, "windSpeedMinKPH": 11, "windSpeedMinMPH": 7, "windSpeedMinMPS": 3, "windDir80m": "W", "windDir80mDEG": 278, "windSpeed80mKTS": 12, "windSpeed80mKPH": 22, "windSpeed80mMPH": 13, "windSpeed80mMPS": 6, "windGust80mKTS": 14, "windGust80mKPH": 25, "windGust80mMPH": 16, "windGust80mMPS": 7, "windDirMax80m": "W", "windDirMax80mDEG": 264, "windSpeedMax80mKTS": 14, "windSpeedMax80mKPH": 25, "windSpeedMax80mMPH": 16, "windSpeedMax80mMPS": 7, "windDirMin80m": "W", "windDirMin80mDEG": 278, "windSpeedMin80mKTS": 12, "windSpeedMin80mKPH": 22, "windSpeedMin80mMPH": 13, "windSpeedMin80mMPS": 6, "sky": 0, "cloudsCoded": "CL", "weather": "Clear", "weatherCoded": [], "weatherPrimary": "Clear", "weatherPrimaryCoded": "::CL", "icon": "clearn.png", "visibilityKM": 16, "visibilityMI": 9.94, "uvi": 0, "solradWM2": 0, "solradMinWM2": 0, "solradMaxWM2": 0, "isDay": false, "ghi": 0, "solrad": {"azimuthDEG": 199.3262, "zenithDEG": 141.7602, "ghiWM2": 0, "dniWM2": 0, "dhiWM2": 0, "version": "v2"}, "solradClearSkyWM2": 0, "solradClearSkySource": "v2", "maxCoverage": "", "spressureMB": 1014, "spressureIN": 29.93, "altimeterMB": 1015, "altimeterIN": 29.98}, {"timestamp": 1759039200, "validTime": "2025-09-28T03:00:00-03:00", "dateTimeISO": "2025-09-28T03:00:00-03:00", "maxTempC": 10.1, "maxTempF": 50, "minTempC": 9, "minTempF": 48, "avgTempC": 9.6, "avgTempF": 49, "tempC": 10.1, "tempF": 50, "wetBulbGlobeTempC": 10, "wetBulbGlobeTempF": 50, "maxFeelslikeC": 10.1, "maxFeelslikeF": 50, "minFeelslikeC": 7.4, "minFeelslikeF": 45, "avgFeelslikeC": 8.8, "avgFeelslikeF": 48, "feelslikeC": 10.1, "feelslikeF": 50, "maxDewpointC": 6.6, "maxDewpointF": 44, "minDewpointC": 6.1, "minDewpointF": 43, "avgDewpointC": 6.4, "avgDewpointF": 44, "dewpointC": 6.6, "dewpointF": 44, "maxHumidity": 82, "minHumidity": 79, "humidity": 79, "pop": 0, "precipMM": 0, "precipIN": 0, "iceaccum": null, "iceaccumMM": null, "iceaccumIN": null, "snowCM": 0, "snowIN": 0, "pressureMB": 1015, "pressureIN": 29.97, "windDir": "WSW", "windDirDEG": 256, "windSpeedKTS": 6, "windSpeedKPH": 11, "windSpeedMPH": 7, "windSpeedMPS": 3, "windGustKTS": 10, "windGustKPH": 18, "windGustMPH": 11, "windGustMPS": 5, "windDirMax": "WSW", "windDirMaxDEG": 256, "windSpeedMaxKTS": 6, "windSpeedMaxKPH": 11, "windSpeedMaxMPH": 7, "windSpeedMaxMPS": 3, "windDirMin": "WSW", "windDirMinDEG": 252, "windSpeedMinKTS": 5, "windSpeedMinKPH": 9, "windSpeedMinMPH": 6, "windSpeedMinMPS": 3, "windDir80m": "WSW", "windDir80mDEG": 257, "windSpeed80mKTS": 13, "windSpeed80mKPH": 23, "windSpeed80mMPH": 15, "windSpeed80mMPS": 7, "windGust80mKTS": 13, "windGust80mKPH": 23, "windGust80mMPH": 15, "windGust80mMPS": 7, "windDirMax80m": "WSW", "windDirMax80mDEG": 257, "windSpeedMax80mKTS": 13, "windSpeedMax80mKPH": 23, "windSpeedMax80mMPH": 15, "windSpeedMax80mMPS": 7, "windDirMin80m": "WSW", "windDirMin80mDEG": 253, "windSpeedMin80mKTS": 10, "windSpeedMin80mKPH": 18, "windSpeedMin80mMPH": 11, "windSpeedMin80mMPS": 5, "sky": 0, "cloudsCoded": "CL", "weather": "Clear", "weatherCoded": [], "weatherPrimary": "Clear", "weatherPrimaryCoded": "::CL", "icon": "clearn.png", "visibilityKM": 16, "visibilityMI": 9.94, "uvi": 0, "solradWM2": 0, "solradMinWM2": 0, "solradMaxWM2": 0, "isDay": false, "ghi": 0, "solrad": {"azimuthDEG": 132.6619, "zenithDEG": 131.9393, "ghiWM2": 0, "dniWM2": 0, "dhiWM2": 0, "version": "v2"}, "solradClearSkyWM2": 0, "solradClearSkySource": "v2", "maxCoverage": "", "spressureMB": 1013, "spressureIN": 29.91, "altimeterMB": 1015, "altimeterIN": 29.96}], "profile": {"tz": "America/Argentina/Buenos_Aires", "elevM": 17, "elevFT": 56}}]}], "forecast_1hr": [{"success": true, "error": null, "response": [{"loc": {"long": -59.033, "lat": -34.682}, "interval": "1hr", "place": {"name": "lujan", "state": "df", "country": "ar"}, "periods": [{"timestamp": 1758963600, "validTime": "2025-09-27T06:00:00-03:00", "dateTimeISO": "2025-09-27T06:00:00-03:00", "maxTempC": 14.1, "maxTempF": 57, "minTempC": 14.1, "minTempF": 57, "avgTempC": 14.1, "avgTempF": 57, "tempC": 14.1, "tempF": 57, "wetBulbGlobeTempC": 13.5, "wetBulbGlobeTempF": 56, "maxFeelslikeC": 14.1, "maxFeelslikeF": 57, "minFeelslikeC": 14.1, "minFeelslikeF": 57, "avgFeelslikeC": 14.1, "avgFeelslikeF": 57, "feelslikeC": 14.1, "feelslikeF": 57, "maxDewpointC": 12.7, "maxDewpointF": 55, "minDewpointC": 12.7, "minDewpointF": 55, "avgDewpointC": 12.7, "avgDewpointF": 55, "dewpointC": 12.7, "dewpointF": 55, "maxHumidity": 91, "minHumidity": 91, "humidity": 91, "pop": 100, "precipMM": 3.1, "precipIN": 0.12, "iceaccum": null, "iceaccumMM": null, "iceaccumIN": null, "snowCM": 0, "snowIN": 0, "pressureMB": 1010, "pressureIN": 29.82, "windDir": "ENE", "windDirDEG": 60, "windSpeedKTS": 10, "windSpeedKPH": 19, "windSpeedMPH": 12, "windSpeedMPS": 5, "windGustKTS": 23, "windGustKPH": 43, "windGustMPH": 27, "windGustMPS": 12, "windDirMax": "ENE", "windDirMaxDEG": 60, "windSpeedMaxKTS": 10, "windSpeedMaxKPH": 19, "windSpeedMaxMPH": 12, "windSpeedMaxMPS": 5, "windDirMin": "ENE", "windDirMinDEG": 60, "windSpeedMinKTS": 10, "windSpeedMinKPH": 19, "windSpeedMinMPH": 12, "windSpeedMinMPS": 5, "windDir80m": "NE", "windDir80mDEG": 38, "windSpeed80mKTS": 16, "windSpeed80mKPH": 29, "windSpeed80mMPH": 18, "windSpeed80mMPS": 8, "windGust80mKTS": 16, "windGust80mKPH": 29, "windGust80mMPH": 18, "windGust80mMPS": 8, "windDirMax80m": "NE", "windDirMax80mDEG": 38, "windSpeedMax80mKTS": 16, "windSpeedMax80mKPH": 29, "windSpeedMax80mMPH": 18, "windSpeedMax80mMPS": 8, "windDirMin80m": "NE", "windDirMin80mDEG": 38, "windSpeedMin80mKTS": 16, "windSpeedMin80mKPH": 29, "windSpeedMin80mMPH": 18, "windSpeedMin80mMPS": 8, "sky": 100, "cloudsCoded": "OV", "weather": "Cloudy with Rain Likely", "weatherCoded": [{"timestamp": 1758963600, "wx": "L::R", "dateTimeISO": "2025-09-27T06:00:00-03:00"}], "weatherPrimary": "Rain", "weatherPrimaryCoded": "L::R", "icon": "rainn.png", "visibilityKM": 2.3066, "visibilityMI": 1.43, "uvi": 0, "solradWM2": 0, "solradMinWM2": 0, "solradMaxWM2": 0, "isDay": false, "ghi": 0, "solrad": {"azimuthDEG": 98.1707, "zenithDEG": 98.8167, "ghiWM2": 0, "dniWM2": 0, "dhiWM2": 0, "version": "v2"}, "solradClearSkyWM2": 0, "solradClearSkySource": "v2", "maxCoverage": "L", "spressureMB": 1008, "spressureIN": 29.76, "altimeterMB": 1009, "altimeterIN": 29.81}, {"timestamp": 1758967200, "validTime": "2025-09-27T07:00:00-03:00", "dateTimeISO": "2025-09-27T07:00:00-03:00", "maxTempC": 14.1, "maxTempF": 57, "minTempC": 14.1, "minTempF": 57, "avgTempC": 14.1, "avgTempF": 57, "tempC": 14.1, "tempF": 57, "wetBulbGlobeTempC": 13.6, "wetBulbGlobeTempF": 57, "maxFeelslikeC": 14.1, "maxFeelslikeF": 57, "minFeelslikeC": 14.1, "minFeelslikeF": 57, "avgFeelslikeC": 14.1, "avgFeelslikeF": 57, "feelslikeC": 14.1, "feelslikeF": 57, "maxDewpointC": 12.8, "maxDewpointF": 55, "minDewpointC": 12.8, "minDewpointF": 55, "avgDewpointC": 12.8, "avgDewpointF": 55, "dewpointC": 12.8, "dewpointF": 55, "maxHumidity": 92, "minHumidity": 92, "humidity": 92, "pop": 10, "precipMM": 3.5, "precipIN": 0.14, "iceaccum": null, "iceaccumMM": null, "iceaccumIN": null, "snowCM": 0, "snowIN": 0, "pressureMB": 1008, "pressureIN": 29.77, "windDir": "ENE", "windDirDEG": 59, "windSpeedKTS": 14, "windSpeedKPH": 27, "windSpeedMPH": 17, "windSpeedMPS": 7, "windGustKTS": 27, "windGustKPH": 50, "windGustMPH": 31, "windGustMPS": 14, "windDirMax": "ENE", "windDirMaxDEG": 59, "windSpeedMaxKTS": 14, "windSpeedMaxKPH": 27, "windSpeedMaxMPH": 17, "windSpeedMaxMPS": 7, "windDirMin": "ENE", "windDirMinDEG": 59, "windSpeedMinKTS": 14, "windSpeedMinKPH": 27, "windSpeedMinMPH": 17, "windSpeedMinMPS": 7, "windDir80m": "NE", "windDir80mDEG": 49, "windSpeed80mKTS": 20, "windSpeed80mKPH": 37, "windSpeed80mMPH": 23, "windSpeed80mMPS": 10, "windGust80mKTS": 20, "windGust80mKPH": 37, "windGust80mMPH": 23, "windGust80mMPS": 10, "windDirMax80m": "NE", "windDirMax80mDEG": 49, "windSpeedMax80mKTS": 20, "windSpeedMax80mKPH": 37, "windSpeedMax80mMPH": 23, "windSpeedMax80mMPS": 10, "windDirMin80m": "NE", "windDirMin80mDEG": 49, "windSpeedMin80mKTS": 20, "windSpeedMin80mKPH": 37, "windSpeedMin80mMPH": 23, "windSpeedMin80mMPS": 10, "sky": 100, "cloudsCoded": "OV", "weather": "Cloudy with Rain Likely", "weatherCoded": [{"timestamp": 1758967200, "wx": "L::R", "dateTimeISO": "2025-09-27T07:00:00-03:00"}], "weatherPrimary": "Rain", "weatherPrimaryCoded": "L::R", "icon": "rain.png", "visibilityKM": 4.35, "visibilityMI": 2.7, "uvi": 0, "solradWM2": 4, "solradMinWM2": 4.0325, "solradMaxWM2": 4.0325, "isDay": true, "ghi": 16.1, "solrad": {"azimuthDEG": 89.5747, "zenithDEG": 86.509, "ghiWM2": 4.0325, "dniWM2": 0, "dhiWM2": 4.0325, "version": "v2"}, "solradClearSkyWM2": 16.13, "solradClearSkySource": "v2", "maxCoverage": "L", "spressureMB": 1006, "spressureIN": 29.71, "altimeterMB": 1008, "altimeterIN": 29.76}, {"timestamp": 1758970800, "validTime": "2025-09-27T08:00:00-03:00", "dateTimeISO": "2025-09-27T08:00:00-03:00", "maxTempC": 14.2, "maxTempF": 58, "minTempC": 14.2, "minTempF": 58, "avgTempC": 14.2, "avgTempF": 58, "tempC": 14.2, "tempF": 58, "wetBulbGlobeTempC": 14, "wetBulbGlobeTempF": 57, "maxFeelslikeC": 14.2, "maxFeelslikeF": 58, "minFeelslikeC": 14.2, "minFeelslikeF": 58, "avgFeelslikeC": 14.2, "avgFeelslikeF": 58, "feelslikeC": 14.2, "feelslikeF": 58, "maxDewpointC": 13.1, "maxDewpointF": 56, "minDewpointC": 13.1, "minDewpointF": 56, "avgDewpointC": 13.1, "avgDewpointF": 56, "dewpointC": 13.1, "dewpointF": 56, "maxHumidity": 93, "minHumidity": 93, "humidity": 93, "pop": 10, "precipMM": 0.2, "precipIN": 0.01, "iceaccum": null, "iceaccumMM": null, "iceaccumIN": null, "snowCM": 0, "snowIN": 0, "pressureMB": 1008, "pressureIN": 29.77, "windDir": "NE", "windDirDEG": 49, "windSpeedKTS": 14, "windSpeedKPH": 25, "windSpeedMPH": 16, "windSpeedMPS": 7, "windGustKTS": 25, "windGustKPH": 47, "windGustMPH": 29, "windGustMPS": 13, "windDirMax": "NE", "windDirMaxDEG": 49, "windSpeedMaxKTS": 14, "windSpeedMaxKPH": 25, "windSpeedMaxMPH": 16, "windSpeedMaxMPS": 7, "windDirMin": "NE", "windDirMinDEG": 49, "windSpeedMinKTS": 14, "windSpeedMinKPH": 25, "windSpeedMinMPH": 16, "windSpeedMinMPS": 7, "windDir80m": "NNE", "windDir80mDEG": 29, "windSpeed80mKTS": 23, "windSpeed80mKPH": 43, "windSpeed80mMPH": 27, "windSpeed80mMPS": 12, "windGust80mKTS": 23, "windGust80mKPH": 43, "windGust80mMPH": 27, "windGust80mMPS": 12, "windDirMax80m": "NNE", "windDirMax80mDEG": 29, "windSpeedMax80mKTS": 23, "windSpeedMax80mKPH": 43, "windSpeedMax80mMPH": 27, "windSpeedMax80mMPS": 12, "windDirMin80m": "NNE", "windDirMin80mDEG": 29, "windSpeedMin80mKTS": 23, "windSpeedMin80mKPH": 43, "windSpeedMin80mMPH": 27, "windSpeedMin80mMPS": 12, "sky": 100, "cloudsCoded": "OV", "weather": "Cloudy with Light Rain Showers", "weatherCoded": [{"timestamp": 1758970800, "wx": ":VL:RW", "dateTimeISO": "2025-09-27T08:00:00-03:00"}], "weatherPrimary": "Rain Showers", "weatherPrimaryCoded": ":VL:RW", "icon": "showers.png", "visibilityKM": 16, "visibilityMI": 9.94, "uvi": 0, "solradWM2": 52, "solradMinWM2": 51.6925, "solradMaxWM2": 51.6925, "isDay": true, "ghi": 206.8, "solrad": {"azimuthDEG": 80.8422, "zenithDEG": 74.2162, "ghiWM2": 51.6925, "dniWM2": 0, "dhiWM2": 51.6925, "version": "v2"}, "solradClearSkyWM2": 206.77, "solradClearSkySource": "v2", "maxCoverage": "", "spressureMB": 1006, "spressureIN": 29.71, "altimeterMB": 1008, "altimeterIN": 29.76}, {"timestamp": 1758974400, "validTime": "2025-09-27T09:00:00-03:00", "dateTimeISO": "2025-09-27T09:00:00-03:00", "maxTempC": 14.3, "maxTempF": 58, "minTempC": 14.3, "minTempF": 58, "avgTempC": 14.3, "avgTempF": 58, "tempC": 14.3, "tempF": 58, "wetBulbGlobeTempC": 14.2, "wetBulbGlobeTempF": 58, "maxFeelslikeC": 14.3, "maxFeelslikeF": 58, "minFeelslikeC": 14.3, "minFeelslikeF": 58, "avgFeelslikeC": 14.3, "avgFeelslikeF": 58, "feelslikeC": 14.3, "feelslikeF": 58, "maxDewpointC": 13.1, "maxDewpointF": 56, "minDewpointC": 13.1, "minDewpointF": 56, "avgDewpointC": 13.1, "avgDewpointF": 56, "dewpointC": 13.1, "dewpointF": 56, "maxHumidity": 93, "minHumidity": 93, "humidity": 93, "pop": 10, "precipMM": 0.1, "precipIN": 0, "iceaccum": null, "iceaccumMM": null, "iceaccumIN": null, "snowCM": 0, "snowIN": 0, "pressureMB": 1008, "pressureIN": 29.77, "windDir": "NE", "windDirDEG": 42, "windSpeedKTS": 12, "windSpeedKPH": 23, "windSpeedMPH": 14, "windSpeedMPS": 6, "windGustKTS": 23, "windGustKPH": 43, "windGustMPH": 27, "windGustMPS": 12, "windDirMax": "NE", "windDirMaxDEG": 42, "windSpeedMaxKTS": 12, "windSpeedMaxKPH": 23, "windSpeedMaxMPH": 14, "windSpeedMaxMPS": 6, "windDirMin": "NE", "windDirMinDEG": 42, "windSpeedMinKTS": 12, "windSpeedMinKPH": 23, "windSpeedMinMPH": 14, "windSpeedMinMPS": 6, "windDir80m": "N", "windDir80mDEG": 11, "windSpeed80mKTS": 23, "windSpeed80mKPH": 43, "windSpeed80mMPH": 27, "windSpeed80mMPS": 12, "windGust80mKTS": 23, "windGust80mKPH": 43, "windGust80mMPH": 27, "windGust80mMPS": 12, "windDirMax80m": "N", "windDirMax80mDEG": 11, "windSpeedMax80mKTS": 23, "windSpeedMax80mKPH": 43, "windSpeedMax80mMPH": 27, "windSpeedMax80mMPS": 12, "windDirMin80m": "N", "windDirMin80mDEG": 11, "windSpeedMin80mKTS": 23, "windSpeedMin80mKPH": 43, "windSpeedMin80mMPH": 27, "windSpeedMin80mMPS": 12, "sky": 100, "cloudsCoded": "OV", "weather": "Cloudy with Light Rain Showers", "weatherCoded": [{"timestamp": 1758974400, "wx": ":VL:RW", "dateTimeISO": "2025-09-27T09:00:00-03:00"}], "weatherPrimary": "Rain Showers", "weatherPrimaryCoded": ":VL:RW", "icon": "showers.png", "visibilityKM": 7.953, "visibilityMI": 4.94, "uvi": 0, "solradWM2": 106, "solradMinWM2": 105.665, "solradMaxWM2": 105.665, "isDay": true, "ghi": 422.7, "solrad": {"azimuthDEG": 71.0871, "zenithDEG": 62.2448, "ghiWM2": 105.665, "dniWM2": 13.1161, "dhiWM2": 99.5569, "version": "v2"}, "solradClearSkyWM2": 422.66, "solradClearSkySource": "v2", "maxCoverage": "", "spressureMB": 1006, "spressureIN": 29.71, "altimeterMB": 1008, "altimeterIN": 29.76}, {"timestamp": 1758978000, "validTime": "2025-09-27T10:00:00-03:00", "dateTimeISO": "2025-09-27T10:00:00-03:00", "maxTempC": 15.3, "maxTempF": 60, "minTempC": 15.3, "minTempF": 60, "avgTempC": 15.3, "avgTempF": 60, "tempC": 15.3, "tempF": 60, "wetBulbGlobeTempC": 15.3, "wetBulbGlobeTempF": 60, "maxFeelslikeC": 15.3, "maxFeelslikeF": 60, "minFeelslikeC": 15.3, "minFeelslikeF": 60, "avgFeelslikeC": 15.3, "avgFeelslikeF": 60, "feelslikeC": 15.3, "feelslikeF": 60, "maxDewpointC": 14, "maxDewpointF": 57, "minDewpointC": 14, "minDewpointF": 57, "avgDewpointC": 14, "avgDewpointF": 57, "dewpointC": 14, "dewpointF": 57, "maxHumidity": 92, "minHumidity": 92, "humidity": 92, "pop": 10, "precipMM": 0.1, "precipIN": 0.01, "iceaccum": null, "iceaccumMM": null, "iceaccumIN": null, "snowCM": 0, "snowIN": 0, "pressureMB": 1007, "pressureIN": 29.75, "windDir": "NE", "windDirDEG": 40, "windSpeedKTS": 10, "windSpeedKPH": 19, "windSpeedMPH": 12, "windSpeedMPS": 5, "windGustKTS": 20, "windGustKPH": 37, "windGustMPH": 23, "windGustMPS": 10, "windDirMax": "NE", "windDirMaxDEG": 40, "windSpeedMaxKTS": 10, "windSpeedMaxKPH": 19, "windSpeedMaxMPH": 12, "windSpeedMaxMPS": 5, "windDirMin": "NE", "windDirMinDEG": 40, "windSpeedMinKTS": 10, "windSpeedMinKPH": 19, "windSpeedMinMPH": 12, "windSpeedMinMPS": 5, "windDir80m": "NNW", "windDir80mDEG": 348, "windSpeed80mKTS": 24, "windSpeed80mKPH": 44, "windSpeed80mMPH": 28, "windSpeed80mMPS": 12, "windGust80mKTS": 24, "windGust80mKPH": 44, "windGust80mMPH": 28, "windGust80mMPS": 12, "windDirMax80m": "NNW", "windDirMax80mDEG": 348, "windSpeedMax80mKTS": 24, "windSpeedMax80mKPH": 44, "windSpeedMax80mMPH": 28, "windSpeedMax80mMPS": 12, "windDirMin80m": "NNW", "windDirMin80mDEG": 348, "windSpeedMin80mKTS": 24, "windSpeedMin80mKPH": 44, "windSpeedMin80mMPH": 28, "windSpeedMin80mMPS": 12, "sky": 100, "cloudsCoded": "OV", "weather": "Cloudy with Light Rain Showers", "weatherCoded": [{"timestamp": 1758978000, "wx": ":VL:RW", "dateTimeISO": "2025-09-27T10:00:00-03:00"}], "weatherPrimary": "Rain Showers", "weatherPrimaryCoded": ":VL:RW", "icon": "showers.png", "visibilityKM": 12.1761, "visibilityMI": 7.57, "uvi": 0, "solradWM2": 152, "solradMinWM2": 152.46, "solradMaxWM2": 152.46, "isDay": true, "ghi": 609.8, "solrad": {"azimuthDEG": 59.1001, "zenithDEG": 51.0415, "ghiWM2": 152.46, "dniWM2": 25.7663, "dhiWM2": 136.2593, "version": "v2"}, "solradClearSkyWM2": 609.84, "solradClearSkySource": "v2", "maxCoverage": "", "spressureMB": 1005, "spressureIN": 29.69, "altimeterMB": 1007, "altimeterIN": 29.74}, {"timestamp": 1758981600, "validTime": "2025-09-27T11:00:00-03:00", "dateTimeISO": "2025-09-27T11:00:00-03:00", "maxTempC": 16.4, "maxTempF": 61, "minTempC": 16.4, "minTempF": 61, "avgTempC": 16.4, "avgTempF": 61, "tempC": 16.4, "tempF": 61, "wetBulbGlobeTempC": 15.5, "wetBulbGlobeTempF": 60, "maxFeelslikeC": 16.4, "maxFeelslikeF": 61, "minFeelslikeC": 16.4, "minFeelslikeF": 61, "avgFeelslikeC": 16.4, "avgFeelslikeF": 61, "feelslikeC": 16.4, "feelslikeF": 61, "maxDewpointC": 12, "maxDewpointF": 54, "minDewpointC": 12, "minDewpointF": 54, "avgDewpointC": 12, "avgDewpointF": 54, "dewpointC": 12, "dewpointF": 54, "maxHumidity": 75, "minHumidity": 75, "humidity": 75, "pop": 10, "precipMM": 0, "precipIN": 0, "iceaccum": null, "iceaccumMM": null, "iceaccumIN": null, "snowCM": 0, "snowIN": 0, "pressureMB": 1006, "pressureIN": 29.71, "windDir": "NNE", "windDirDEG": 23, "windSpeedKTS": 10, "windSpeedKPH": 18, "windSpeedMPH": 11, "windSpeedMPS": 5, "windGustKTS": 21, "windGustKPH": 39, "windGustMPH": 24, "windGustMPS": 11, "windDirMax": "NNE", "windDirMaxDEG": 23, "windSpeedMaxKTS": 10, "windSpeedMaxKPH": 18, "windSpeedMaxMPH": 11, "windSpeedMaxMPS": 5, "windDirMin": "NNE", "windDirMinDEG": 23, "windSpeedMinKTS": 10, "windSpeedMinKPH": 18, "windSpeedMinMPH": 11, "windSpeedMinMPS": 5, "windDir80m": "NW", "windDir80mDEG": 305, "windSpeed80mKTS": 22, "windSpeed80mKPH": 41, "windSpeed80mMPH": 26, "windSpeed80mMPS": 12, "windGust80mKTS": 22, "windGust80mKPH": 41, "windGust80mMPH": 26, "windGust80mMPS": 12, "windDirMax80m": "NW", "windDirMax80mDEG": 305, "windSpeedMax80mKTS": 22, "windSpeedMax80mKPH": 41, "windSpeedMax80mMPH": 26, "windSpeedMax80mMPS": 12, "windDirMin80m": "NW", "windDirMin80mDEG": 305, "windSpeedMin80mKTS": 22, "windSpeedMin80mKPH": 41, "windSpeedMin80mMPH": 26, "windSpeedMin80mMPS": 12, "sky": 99, "cloudsCoded": "OV", "weather": "Cloudy with Light Rain Showers", "weatherCoded": [{"timestamp": 1758981600, "wx": ":VL:RW", "dateTimeISO": "2025-09-27T11:00:00-03:00"}], "weatherPrimary": "Rain Showers", "weatherPrimaryCoded": ":VL:RW", "icon": "showers.png", "visibilityKM": 13.8505, "visibilityMI": 8.61, "uvi": 0, "solradWM2": 206, "solradMinWM2": 207.9607, "solradMaxWM2": 207.9607, "isDay": true, "ghi": 750.3, "solrad": {"azimuthDEG": 43.0923, "zenithDEG": 41.4019, "ghiWM2": 206.4681, "dniWM2": 34.0753, "dhiWM2": 180.9086, "version": "v2"}, "solradClearSkyWM2": 750.26, "solradClearSkySource": "v2", "maxCoverage": "", "spressureMB": 1004, "spressureIN": 29.65, "altimeterMB": 1006, "altimeterIN": 29.7}, {"timestamp": 1758985200, "validTime": "2025-09-27T12:00:00-03:00", "dateTimeISO": "2025-09-27T12:00:00-03:00", "maxTempC": 17.5, "maxTempF": 63, "minTempC": 17.5, "minTempF": 63, "avgTempC": 17.5, "avgTempF": 63, "tempC": 17.5, "tempF": 63, "wetBulbGlobeTempC": 16.7, "wetBulbGlobeTempF": 62, "maxFeelslikeC": 17.5, "maxFeelslikeF": 63, "minFeelslikeC": 17.5, "minFeelslikeF": 63, "avgFeelslikeC": 17.5, "avgFeelslikeF": 63, "feelslikeC": 17.5, "feelslikeF": 63, "maxDewpointC": 13.3, "maxDewpointF": 56, "minDewpointC": 13.3, "minDewpointF": 56, "avgDewpointC": 13.3, "avgDewpointF": 56, "dewpointC": 13.3, "dewpointF": 56, "maxHumidity": 76, "minHumidity": 76, "humidity": 76, "pop": 10, "precipMM": 0.2, "precipIN": 0.01, "iceaccum": null, "iceaccumMM": null, "iceaccumIN": null, "snowCM": 0, "snowIN": 0, "pressureMB": 1006, "pressureIN": 29.71, "windDir": "NW", "windDirDEG": 325, "windSpeedKTS": 10, "windSpeedKPH": 18, "windSpeedMPH": 11, "windSpeedMPS": 5, "windGustKTS": 21, "windGustKPH": 39, "windGustMPH": 24, "windGustMPS": 11, "windDirMax": "NW", "windDirMaxDEG": 325, "windSpeedMaxKTS": 10, "windSpeedMaxKPH": 18, "windSpeedMaxMPH": 11, "windSpeedMaxMPS": 5, "windDirMin": "NW", "windDirMinDEG": 325, "windSpeedMinKTS": 10, "windSpeedMinKPH": 18, "windSpeedMinMPH": 11, "windSpeedMinMPS": 5, "windDir80m": "W", "windDir80mDEG": 280, "windSpeed80mKTS": 18, "windSpeed80mKPH": 33, "windSpeed80mMPH": 21, "windSpeed80mMPS": 9, "windGust80mKTS": 18, "windGust80mKPH": 33, "windGust80mMPH": 21, "windGust80mMPS": 9, "windDirMax80m": "W", "windDirMax80mDEG": 280, "windSpeedMax80mKTS": 18, "windSpeedMax80mKPH": 33, "windSpeedMax80mMPH": 21, "windSpeedMax80mMPS": 9, "windDirMin80m": "W", "windDirMin80mDEG": 280, "windSpeedMin80mKTS": 18, "windSpeedMin80mKPH": 33, "windSpeedMin80mMPH": 21, "windSpeedMin80mMPS": 9, "sky": 100, "cloudsCoded": "OV", "weather": "Cloudy with Light Rain Showers", "weatherCoded": [{"timestamp": 1758985200, "wx": ":VL:RW", "dateTimeISO": "2025-09-27T12:00:00-03:00"}], "weatherPrimary": "Rain Showers", "weatherPrimaryCoded": ":VL:RW", "icon": "showers.png", "visibilityKM": 14.3386, "visibilityMI": 8.91, "uvi": 0, "solradWM2": 208, "solradMinWM2": 208.2225, "solradMaxWM2": 208.2225, "isDay": true, "ghi": 832.9, "solrad": {"azimuthDEG": 21.1295, "zenithDEG": 34.7718, "ghiWM2": 208.2225, "dniWM2": 34.8774, "dhiWM2": 179.5732, "version": "v2"}, "solradClearSkyWM2": 832.89, "solradClearSkySource": "v2", "maxCoverage": "", "spressureMB": 1004, "spressureIN": 29.65, "altimeterMB": 1006, "altimeterIN": 29.7}, {"timestamp": 1758988800, "validTime": "2025-09-27T13:00:00-03:00", "dateTimeISO": "2025-09-27T13:00:00-03:00", "maxTempC": 17.1, "maxTempF": 63, "minTempC": 17.1, "minTempF": 63, "avgTempC": 17.1, "avgTempF": 63, "tempC": 17.1, "tempF": 63, "wetBulbGlobeTempC": 16.4, "wetBulbGlobeTempF": 62, "maxFeelslikeC": 17.1, "maxFeelslikeF": 63, "minFeelslikeC": 17.1, "minFeelslikeF": 63, "avgFeelslikeC": 17.1, "avgFeelslikeF": 63, "feelslikeC": 17.1, "feelslikeF": 63, "maxDewpointC": 13.1, "maxDewpointF": 56, "minDewpointC": 13.1, "minDewpointF": 56, "avgDewpointC": 13.1, "avgDewpointF": 56, "dewpointC": 13.1, "dewpointF": 56, "maxHumidity": 77, "minHumidity": 77, "humidity": 77, "pop": 10, "precipMM": 0.1, "precipIN": 0, "iceaccum": null, "iceaccumMM": null, "iceaccumIN": null, "snowCM": 0, "snowIN": 0, "pressureMB": 1006, "pressureIN": 29.72, "windDir": "W", "windDirDEG": 272, "windSpeedKTS": 10, "windSpeedKPH": 19, "windSpeedMPH": 12, "windSpeedMPS": 5, "windGustKTS": 18, "windGustKPH": 33, "windGustMPH": 21, "windGustMPS": 9, "windDirMax": "W", "windDirMaxDEG": 272, "windSpeedMaxKTS": 10, "windSpeedMaxKPH": 19, "windSpeedMaxMPH": 12, "windSpeedMaxMPS": 5, "windDirMin": "W", "windDirMinDEG": 272, "windSpeedMinKTS": 10, "windSpeedMinKPH": 19, "windSpeedMinMPH": 12, "windSpeedMinMPS": 5, "windDir80m": "WSW", "windDir80mDEG": 248, "windSpeed80mKTS": 25, "windSpeed80mKPH": 47, "windSpeed80mMPH": 29, "windSpeed80mMPS": 13, "windGust80mKTS": 25, "windGust80mKPH": 47, "windGust80mMPH": 29, "windGust80mMPS": 13, "windDirMax80m": "WSW", "windDirMax80mDEG": 248, "windSpeedMax80mKTS": 25, "windSpeedMax80mKPH": 47, "windSpeedMax80mMPH": 29, "windSpeedMax80mMPS": 13, "windDirMin80m": "WSW", "windDirMin80mDEG": 248, "windSpeedMin80mKTS": 25, "windSpeedMin80mKPH": 47, "windSpeedMin80mMPH": 29, "windSpeedMin80mMPS": 13, "sky": 100, "cloudsCoded": "OV", "weather": "Cloudy with Light Rain Showers", "weatherCoded": [{"timestamp": 1758988800, "wx": ":VL:RW", "dateTimeISO": "2025-09-27T13:00:00-03:00"}], "weatherPrimary": "Rain Showers", "weatherPrimaryCoded": ":VL:RW", "icon": "showers.png", "visibilityKM": 15.9987, "visibilityMI": 9.94, "uvi": 5, "solradWM2": 213, "solradMinWM2": 212.9025, "solradMaxWM2": 212.9025, "isDay": true, "ghi": 851.6, "solrad": {"azimuthDEG": 354.2528, "zenithDEG": 33.0781, "ghiWM2": 212.9025, "dniWM2": 35.4543, "dhiWM2": 183.1944, "version": "v2"}, "solradClearSkyWM2": 851.61, "solradClearSkySource": "v2", "maxCoverage": "", "spressureMB": 1004, "spressureIN": 29.66, "altimeterMB": 1006, "altimeterIN": 29.71}, {"timestamp": 1758992400, "validTime": "2025-09-27T14:00:00-03:00", "dateTimeISO": "2025-09-27T14:00:00-03:00", "maxTempC": 16.7, "maxTempF": 62, "minTempC": 16.7, "minTempF": 62, "avgTempC": 16.7, "avgTempF": 62, "tempC": 16.7, "tempF": 62, "wetBulbGlobeTempC": 15.5, "wetBulbGlobeTempF": 60, "maxFeelslikeC": 16.7, "maxFeelslikeF": 62, "minFeelslikeC": 16.7, "minFeelslikeF": 62, "avgFeelslikeC": 16.7, "avgFeelslikeF": 62, "feelslikeC": 16.7, "feelslikeF": 62, "maxDewpointC": 11.9, "maxDewpointF": 53, "minDewpointC": 11.9, "minDewpointF": 53, "avgDewpointC": 11.9, "avgDewpointF": 53, "dewpointC": 11.9, "dewpointF": 53, "maxHumidity": 74, "minHumidity": 74, "humidity": 74, "pop": 10, "precipMM": 0.2, "precipIN": 0.01, "iceaccum": null, "iceaccumMM": null, "iceaccumIN": null, "snowCM": 0, "snowIN": 0, "pressureMB": 1007, "pressureIN": 29.74, "windDir": "WSW", "windDirDEG": 250, "windSpeedKTS": 15, "windSpeedKPH": 28, "windSpeedMPH": 17, "windSpeedMPS": 8, "windGustKTS": 27, "windGustKPH": 49, "windGustMPH": 31, "windGustMPS": 14, "windDirMax": "WSW", "windDirMaxDEG": 250, "windSpeedMaxKTS": 15, "windSpeedMaxKPH": 28, "windSpeedMaxMPH": 17, "windSpeedMaxMPS": 8, "windDirMin": "WSW", "windDirMinDEG": 250, "windSpeedMinKTS": 15, "windSpeedMinKPH": 28, "windSpeedMinMPH": 17, "windSpeedMinMPS": 8, "windDir80m": "WSW", "windDir80mDEG": 241, "windSpeed80mKTS": 27, "windSpeed80mKPH": 50, "windSpeed80mMPH": 31, "windSpeed80mMPS": 14, "windGust80mKTS": 27, "windGust80mKPH": 50, "windGust80mMPH": 31, "windGust80mMPS": 14, "windDirMax80m": "WSW", "windDirMax80mDEG": 241, "windSpeedMax80mKTS": 27, "windSpeedMax80mKPH": 50, "windSpeedMax80mMPH": 31, "windSpeedMax80mMPS": 14, "windDirMin80m": "WSW", "windDirMin80mDEG": 241, "windSpeedMin80mKTS": 27, "windSpeedMin80mKPH": 50, "windSpeedMin80mMPH": 31, "windSpeedMin80mMPS": 14, "sky": 100, "cloudsCoded": "OV", "weather": "Cloudy with Light Rain Showers", "weatherCoded": [{"timestamp": 1758992400, "wx": ":VL:RW", "dateTimeISO": "2025-09-27T14:00:00-03:00"}], "weatherPrimary": "Rain Showers", "weatherPrimaryCoded": ":VL:RW", "icon": "showers.png", "visibilityKM": 6.793, "visibilityMI": 4.22, "uvi": 3, "solradWM2": 201, "solradMinWM2": 201.2725, "solradMaxWM2": 201.2725, "isDay": true, "ghi": 805.1, "solrad": {"azimuthDEG": 328.8789, "zenithDEG": 37.0159, "ghiWM2": 201.2725, "dniWM2": 33.9442, "dhiWM2": 174.1691, "version": "v2"}, "solradClearSkyWM2": 805.09, "solradClearSkySource": "v2", "maxCoverage": "", "spressureMB": 1005, "spressureIN": 29.68, "altimeterMB": 1007, "altimeterIN": 29.73}, {"timestamp": 1758996000, "validTime": "2025-09-27T15:00:00-03:00", "dateTimeISO": "2025-09-27T15:00:00-03:00", "maxTempC": 16.3, "maxTempF": 61, "minTempC": 16.3, "minTempF": 61, "avgTempC": 16.3, "avgTempF": 61, "tempC": 16.3, "tempF": 61, "wetBulbGlobeTempC": 14.9, "wetBulbGlobeTempF": 59, "maxFeelslikeC": 16.3, "maxFeelslikeF": 61, "minFeelslikeC": 16.3, "minFeelslikeF": 61, "avgFeelslikeC": 16.3, "avgFeelslikeF": 61, "feelslikeC": 16.3, "feelslikeF": 61, "maxDewpointC": 11.4, "maxDewpointF": 52, "minDewpointC": 11.4, "minDewpointF": 52, "avgDewpointC": 11.4, "avgDewpointF": 52, "dewpointC": 11.4, "dewpointF": 52, "maxHumidity": 73, "minHumidity": 73, "humidity": 73, "pop": 10, "precipMM": 0.2, "precipIN": 0.01, "iceaccum": null, "iceaccumMM": null, "iceaccumIN": null, "snowCM": 0, "snowIN": 0, "pressureMB": 1008, "pressureIN": 29.78, "windDir": "SW", "windDirDEG": 234, "windSpeedKTS": 17, "windSpeedKPH": 31, "windSpeedMPH": 19, "windSpeedMPS": 9, "windGustKTS": 31, "windGustKPH": 58, "windGustMPH": 36, "windGustMPS": 16, "windDirMax": "SW", "windDirMaxDEG": 234, "windSpeedMaxKTS": 17, "windSpeedMaxKPH": 31, "windSpeedMaxMPH": 19, "windSpeedMaxMPS": 9, "windDirMin": "SW", "windDirMinDEG": 234, "windSpeedMinKTS": 17, "windSpeedMinKPH": 31, "windSpeedMinMPH": 19, "windSpeedMinMPS": 9, "windDir80m": "SW", "windDir80mDEG": 230, "windSpeed80mKTS": 25, "windSpeed80mKPH": 47, "windSpeed80mMPH": 29, "windSpeed80mMPS": 13, "windGust80mKTS": 25, "windGust80mKPH": 47, "windGust80mMPH": 29, "windGust80mMPS": 13, "windDirMax80m": "SW", "windDirMax80mDEG": 230, "windSpeedMax80mKTS": 25, "windSpeedMax80mKPH": 47, "windSpeedMax80mMPH": 29, "windSpeedMax80mMPS": 13, "windDirMin80m": "SW", "windDirMin80mDEG": 230, "windSpeedMin80mKTS": 25, "windSpeedMin80mKPH": 47, "windSpeedMin80mMPH": 29, "windSpeedMin80mMPS": 13, "sky": 100, "cloudsCoded": "OV", "weather": "Cloudy with Light Rain Showers", "weatherCoded": [{"timestamp": 1758996000, "wx": ":VL:RW", "dateTimeISO": "2025-09-27T15:00:00-03:00"}], "weatherPrimary": "Rain Showers", "weatherPrimaryCoded": ":VL:RW", "icon": "showers.png", "visibilityKM": 16, "visibilityMI": 9.94, "uvi": 0, "solradWM2": 174, "solradMinWM2": 174.1825, "solradMaxWM2": 174.1825, "isDay": true, "ghi": 696.7, "solrad": {"azimuthDEG": 309.527, "zenithDEG": 45.1094, "ghiWM2": 174.1825, "dniWM2": 29.825, "dhiWM2": 153.1334, "version": "v2"}, "solradClearSkyWM2": 696.73, "solradClearSkySource": "v2", "maxCoverage": "", "spressureMB": 1006, "spressureIN": 29.72, "altimeterMB": 1008, "altimeterIN": 29.77}, {"timestamp": 1758999600, "validTime": "2025-09-27T16:00:00-03:00", "dateTimeISO": "2025-09-27T16:00:00-03:00", "maxTempC": 16.3, "maxTempF": 61, "minTempC": 16.3, "minTempF": 61, "avgTempC": 16.3, "avgTempF": 61, "tempC": 16.3, "tempF": 61, "wetBulbGlobeTempC": 14.8, "wetBulbGlobeTempF": 59, "maxFeelslikeC": 16.3, "maxFeelslikeF": 61, "minFeelslikeC": 16.3, "minFeelslikeF": 61, "avgFeelslikeC": 16.3, "avgFeelslikeF": 61, "feelslikeC": 16.3, "feelslikeF": 61, "maxDewpointC": 11.6, "maxDewpointF": 53, "minDewpointC": 11.6, "minDewpointF": 53, "avgDewpointC": 11.6, "avgDewpointF": 53, "dewpointC": 11.6, "dewpointF": 53, "maxHumidity": 74, "minHumidity": 74, "humidity": 74, "pop": 0, "precipMM": 0, "precipIN": 0, "iceaccum": null, "iceaccumMM": null, "iceaccumIN": null, "snowCM": 0, "snowIN": 0, "pressureMB": 1010, "pressureIN": 29.81, "windDir": "SW", "windDirDEG": 226, "windSpeedKTS": 18, "windSpeedKPH": 32, "windSpeedMPH": 20, "windSpeedMPS": 9, "windGustKTS": 33, "windGustKPH": 61, "windGustMPH": 38, "windGustMPS": 17, "windDirMax": "SW", "windDirMaxDEG": 226, "windSpeedMaxKTS": 18, "windSpeedMaxKPH": 32, "windSpeedMaxMPH": 20, "windSpeedMaxMPS": 9, "windDirMin": "SW", "windDirMinDEG": 226, "windSpeedMinKTS": 18, "windSpeedMinKPH": 32, "windSpeedMinMPH": 20, "windSpeedMinMPS": 9, "windDir80m": "WSW", "windDir80mDEG": 241, "windSpeed80mKTS": 23, "windSpeed80mKPH": 43, "windSpeed80mMPH": 27, "windSpeed80mMPS": 12, "windGust80mKTS": 23, "windGust80mKPH": 43, "windGust80mMPH": 27, "windGust80mMPS": 12, "windDirMax80m": "WSW", "windDirMax80mDEG": 241, "windSpeedMax80mKTS": 23, "windSpeedMax80mKPH": 43, "windSpeedMax80mMPH": 27, "windSpeedMax80mMPS": 12, "windDirMin80m": "WSW", "windDirMin80mDEG": 241, "windSpeedMin80mKTS": 23, "windSpeedMin80mKPH": 43, "windSpeedMin80mMPH": 27, "windSpeedMin80mMPS": 12, "sky": 80, "cloudsCoded": "BK", "weather": "Mostly Cloudy", "weatherCoded": [], "weatherPrimary": "Mostly Cloudy", "weatherPrimaryCoded": "::BK", "icon": "mcloudy.png", "visibilityKM": 16, "visibilityMI": 9.94, "uvi": 1, "solradWM2": 347, "solradMinWM2": 348.0424, "solradMaxWM2": 348.0424, "isDay": true, "ghi": 534.7, "solrad": {"azimuthDEG": 295.4263, "zenithDEG": 55.5197, "ghiWM2": 346.9273, "dniWM2": 190.1964, "dhiWM2": 239.2529, "version": "v2"}, "solradClearSkyWM2": 534.73, "solradClearSkySource": "v2", "maxCoverage": "", "spressureMB": 1008, "spressureIN": 29.75, "altimeterMB": 1009, "altimeterIN": 29.8}, {"timestamp": 1759003200, "validTime": "2025-09-27T17:00:00-03:00", "dateTimeISO": "2025-09-27T17:00:00-03:00", "maxTempC": 16.2, "maxTempF": 61, "minTempC": 16.2, "minTempF": 61, "avgTempC": 16.2, "avgTempF": 61, "tempC": 16.2, "tempF": 61, "wetBulbGlobeTempC": 14.5, "wetBulbGlobeTempF": 58, "maxFeelslikeC": 16.2, "maxFeelslikeF": 61, "minFeelslikeC": 16.2, "minFeelslikeF": 61, "avgFeelslikeC": 16.2, "avgFeelslikeF": 61, "feelslikeC": 16.2, "feelslikeF": 61, "maxDewpointC": 11.1, "maxDewpointF": 52, "minDewpointC": 11.1, "minDewpointF": 52, "avgDewpointC": 11.1, "avgDewpointF": 52, "dewpointC": 11.1, "dewpointF": 52, "maxHumidity": 72, "minHumidity": 72, "humidity": 72, "pop": 0, "precipMM": 0, "precipIN": 0, "iceaccum": null, "iceaccumMM": null, "iceaccumIN": null, "snowCM": 0, "snowIN": 0, "pressureMB": 1011, "pressureIN": 29.85, "windDir": "SW", "windDirDEG": 225, "windSpeedKTS": 18, "windSpeedKPH": 33, "windSpeedMPH": 20, "windSpeedMPS": 9, "windGustKTS": 33, "windGustKPH": 62, "windGustMPH": 38, "windGustMPS": 17, "windDirMax": "SW", "windDirMaxDEG": 225, "windSpeedMaxKTS": 18, "windSpeedMaxKPH": 33, "windSpeedMaxMPH": 20, "windSpeedMaxMPS": 9, "windDirMin": "SW", "windDirMinDEG": 225, "windSpeedMinKTS": 18, "windSpeedMinKPH": 33, "windSpeedMinMPH": 20, "windSpeedMinMPS": 9, "windDir80m": "WSW", "windDir80mDEG": 242, "windSpeed80mKTS": 24, "windSpeed80mKPH": 45, "windSpeed80mMPH": 28, "windSpeed80mMPS": 13, "windGust80mKTS": 24, "windGust80mKPH": 45, "windGust80mMPH": 28, "windGust80mMPS": 13, "windDirMax80m": "WSW", "windDirMax80mDEG": 242, "windSpeedMax80mKTS": 24, "windSpeedMax80mKPH": 45, "windSpeedMax80mMPH": 28, "windSpeedMax80mMPS": 13, "windDirMin80m": "WSW", "windDirMin80mDEG": 242, "windSpeedMin80mKTS": 24, "windSpeedMin80mKPH": 45, "windSpeedMin80mMPH": 28, "windSpeedMin80mMPS": 13, "sky": 54, "cloudsCoded": "SC", "weather": "Partly Cloudy", "weatherCoded": [], "weatherPrimary": "Partly Cloudy", "weatherPrimaryCoded": "::SC", "icon": "pcloudy.png", "visibilityKM": 16, "visibilityMI": 9.94, "uvi": 1, "solradWM2": 302, "solradMinWM2": 300.9576, "solradMaxWM2": 300.9576, "isDay": true, "ghi": 332.6, "solrad": {"azimuthDEG": 284.5278, "zenithDEG": 67.1015, "ghiWM2": 301.8558, "dniWM2": 501.5443, "dhiWM2": 106.7049, "version": "v2"}, "solradClearSkyWM2": 332.55, "solradClearSkySource": "v2", "maxCoverage": "", "spressureMB": 1009, "spressureIN": 29.79, "altimeterMB": 1011, "altimeterIN": 29.84}, {"timestamp": 1759006800, "validTime": "2025-09-27T18:00:00-03:00", "dateTimeISO": "2025-09-27T18:00:00-03:00", "maxTempC": 16.1, "maxTempF": 61, "minTempC": 16.1, "minTempF": 61, "avgTempC": 16.1, "avgTempF": 61, "tempC": 16.1, "tempF": 61, "wetBulbGlobeTempC": 14, "wetBulbGlobeTempF": 57, "maxFeelslikeC": 16.1, "maxFeelslikeF": 61, "minFeelslikeC": 16.1, "minFeelslikeF": 61, "avgFeelslikeC": 16.1, "avgFeelslikeF": 61, "feelslikeC": 16.1, "feelslikeF": 61, "maxDewpointC": 10, "maxDewpointF": 50, "minDewpointC": 10, "minDewpointF": 50, "avgDewpointC": 10, "avgDewpointF": 50, "dewpointC": 10, "dewpointF": 50, "maxHumidity": 67, "minHumidity": 67, "humidity": 67, "pop": 0, "precipMM": 0, "precipIN": 0, "iceaccum": null, "iceaccumMM": null, "iceaccumIN": null, "snowCM": 0, "snowIN": 0, "pressureMB": 1012, "pressureIN": 29.87, "windDir": "SW", "windDirDEG": 225, "windSpeedKTS": 14, "windSpeedKPH": 25, "windSpeedMPH": 16, "windSpeedMPS": 7, "windGustKTS": 25, "windGustKPH": 45, "windGustMPH": 28, "windGustMPS": 13, "windDirMax": "SW", "windDirMaxDEG": 225, "windSpeedMaxKTS": 14, "windSpeedMaxKPH": 25, "windSpeedMaxMPH": 16, "windSpeedMaxMPS": 7, "windDirMin": "SW", "windDirMinDEG": 225, "windSpeedMinKTS": 14, "windSpeedMinKPH": 25, "windSpeedMinMPH": 16, "windSpeedMinMPS": 7, "windDir80m": "SW", "windDir80mDEG": 234, "windSpeed80mKTS": 22, "windSpeed80mKPH": 41, "windSpeed80mMPH": 26, "windSpeed80mMPS": 12, "windGust80mKTS": 22, "windGust80mKPH": 41, "windGust80mMPH": 26, "windGust80mMPS": 12, "windDirMax80m": "SW", "windDirMax80mDEG": 234, "windSpeedMax80mKTS": 22, "windSpeedMax80mKPH": 41, "windSpeedMax80mMPH": 26, "windSpeedMax80mMPS": 12, "windDirMin80m": "SW", "windDirMin80mDEG": 234, "windSpeedMin80mKTS": 22, "windSpeedMin80mKPH": 41, "windSpeedMin80mMPH": 26, "windSpeedMin80mMPS": 12, "sky": 19, "cloudsCoded": "FW", "weather": "Mostly Sunny", "weatherCoded": [], "weatherPrimary": "Mostly Sunny", "weatherPrimaryCoded": "::FW", "icon": "fair.png", "visibilityKM": 16, "visibilityMI": 9.94, "uvi": 0, "solradWM2": 115, "solradMinWM2": 114.6213, "solradMaxWM2": 114.6213, "isDay": true, "ghi": 114.9, "solrad": {"azimuthDEG": 275.2991, "zenithDEG": 79.2357, "ghiWM2": 114.6357, "dniWM2": 320.8253, "dhiWM2": 54.7153, "version": "v2"}, "solradClearSkyWM2": 114.94, "solradClearSkySource": "v2", "maxCoverage": "", "spressureMB": 1010, "spressureIN": 29.81, "altimeterMB": 1011, "altimeterIN": 29.87}, {"timestamp": 1759010400, "validTime": "2025-09-27T19:00:00-03:00", "dateTimeISO": "2025-09-27T19:00:00-03:00", "maxTempC": 15.4, "maxTempF": 60, "minTempC": 15.4, "minTempF": 60, "avgTempC": 15.4, "avgTempF": 60, "tempC": 15.4, "tempF": 60, "wetBulbGlobeTempC": 12.9, "wetBulbGlobeTempF": 55, "maxFeelslikeC": 15.4, "maxFeelslikeF": 60, "minFeelslikeC": 15.4, "minFeelslikeF": 60, "avgFeelslikeC": 15.4, "avgFeelslikeF": 60, "feelslikeC": 15.4, "feelslikeF": 60, "maxDewpointC": 9, "maxDewpointF": 48, "minDewpointC": 9, "minDewpointF": 48, "avgDewpointC": 9, "avgDewpointF": 48, "dewpointC": 9, "dewpointF": 48, "maxHumidity": 66, "minHumidity": 66, "humidity": 66, "pop": 0, "precipMM": 0, "precipIN": 0, "iceaccum": null, "iceaccumMM": null, "iceaccumIN": null, "snowCM": 0, "snowIN": 0, "pressureMB": 1013, "pressureIN": 29.9, "windDir": "SW", "windDirDEG": 231, "windSpeedKTS": 11, "windSpeedKPH": 20, "windSpeedMPH": 12, "windSpeedMPS": 6, "windGustKTS": 20, "windGustKPH": 37, "windGustMPH": 23, "windGustMPS": 10, "windDirMax": "SW", "windDirMaxDEG": 231, "windSpeedMaxKTS": 11, "windSpeedMaxKPH": 20, "windSpeedMaxMPH": 12, "windSpeedMaxMPS": 6, "windDirMin": "SW", "windDirMinDEG": 231, "windSpeedMinKTS": 11, "windSpeedMinKPH": 20, "windSpeedMinMPH": 12, "windSpeedMinMPS": 6, "windDir80m": "SW", "windDir80mDEG": 235, "windSpeed80mKTS": 20, "windSpeed80mKPH": 38, "windSpeed80mMPH": 23, "windSpeed80mMPS": 10, "windGust80mKTS": 20, "windGust80mKPH": 38, "windGust80mMPH": 23, "windGust80mMPS": 10, "windDirMax80m": "SW", "windDirMax80mDEG": 235, "windSpeedMax80mKTS": 20, "windSpeedMax80mKPH": 38, "windSpeedMax80mMPH": 23, "windSpeedMax80mMPS": 10, "windDirMin80m": "SW", "windDirMin80mDEG": 235, "windSpeedMin80mKTS": 20, "windSpeedMin80mKPH": 38, "windSpeedMin80mMPH": 23, "windSpeedMin80mMPS": 10, "sky": 15, "cloudsCoded": "FW", "weather": "Mostly Clear", "weatherCoded": [], "weatherPrimary": "Mostly Clear", "weatherPrimaryCoded": "::FW", "icon": "fairn.png", "visibilityKM": 16, "visibilityMI": 9.94, "uvi": 0, "solradWM2": 0, "solradMinWM2": 0, "solradMaxWM2": 0, "isDay": false, "ghi": 0, "solrad": {"azimuthDEG": 266.6978, "zenithDEG": 91.5507, "ghiWM2": 0, "dniWM2": 0, "dhiWM2": 0, "version": "v2"}, "solradClearSkyWM2": 0, "solradClearSkySource": "v2", "maxCoverage": "", "spressureMB": 1011, "spressureIN": 29.84, "altimeterMB": 1012, "altimeterIN": 29.89}, {"timestamp": 1759014000, "validTime": "2025-09-27T20:00:00-03:00", "dateTimeISO": "2025-09-27T20:00:00-03:00", "maxTempC": 14.6, "maxTempF": 58, "minTempC": 14.6, "minTempF": 58, "avgTempC": 14.6, "avgTempF": 58, "tempC": 14.6, "tempF": 58, "wetBulbGlobeTempC": 12.3, "wetBulbGlobeTempF": 54, "maxFeelslikeC": 14.6, "maxFeelslikeF": 58, "minFeelslikeC": 14.6, "minFeelslikeF": 58, "avgFeelslikeC": 14.6, "avgFeelslikeF": 58, "feelslikeC": 14.6, "feelslikeF": 58, "maxDewpointC": 8.7, "maxDewpointF": 48, "minDewpointC": 8.7, "minDewpointF": 48, "avgDewpointC": 8.7, "avgDewpointF": 48, "dewpointC": 8.7, "dewpointF": 48, "maxHumidity": 68, "minHumidity": 68, "humidity": 68, "pop": 0, "precipMM": 0, "precipIN": 0, "iceaccum": null, "iceaccumMM": null, "iceaccumIN": null, "snowCM": 0, "snowIN": 0, "pressureMB": 1014, "pressureIN": 29.94, "windDir": "SW", "windDirDEG": 232, "windSpeedKTS": 11, "windSpeedKPH": 21, "windSpeedMPH": 13, "windSpeedMPS": 6, "windGustKTS": 20, "windGustKPH": 38, "windGustMPH": 24, "windGustMPS": 11, "windDirMax": "SW", "windDirMaxDEG": 232, "windSpeedMaxKTS": 11, "windSpeedMaxKPH": 21, "windSpeedMaxMPH": 13, "windSpeedMaxMPS": 6, "windDirMin": "SW", "windDirMinDEG": 232, "windSpeedMinKTS": 11, "windSpeedMinKPH": 21, "windSpeedMinMPH": 13, "windSpeedMinMPS": 6, "windDir80m": "WSW", "windDir80mDEG": 240, "windSpeed80mKTS": 18, "windSpeed80mKPH": 33, "windSpeed80mMPH": 20, "windSpeed80mMPS": 9, "windGust80mKTS": 18, "windGust80mKPH": 33, "windGust80mMPH": 20, "windGust80mMPS": 9, "windDirMax80m": "WSW", "windDirMax80mDEG": 240, "windSpeedMax80mKTS": 18, "windSpeedMax80mKPH": 33, "windSpeedMax80mMPH": 20, "windSpeedMax80mMPS": 9, "windDirMin80m": "WSW", "windDirMin80mDEG": 240, "windSpeedMin80mKTS": 18, "windSpeedMin80mKPH": 33, "windSpeedMin80mMPH": 20, "windSpeedMin80mMPS": 9, "sky": 29, "cloudsCoded": "FW", "weather": "Mostly Clear", "weatherCoded": [], "weatherPrimary": "Mostly Clear", "weatherPrimaryCoded": "::FW", "icon": "fairn.png", "visibilityKM": 16, "visibilityMI": 9.94, "uvi": 0, "solradWM2": 0, "solradMinWM2": 0, "solradMaxWM2": 0, "isDay": false, "ghi": 0, "solrad": {"azimuthDEG": 257.8909, "zenithDEG": 103.7571, "ghiWM2": 0, "dniWM2": 0, "dhiWM2": 0, "version": "v2"}, "solradClearSkyWM2": 0, "solradClearSkySource": "v2", "maxCoverage": "", "spressureMB": 1012, "spressureIN": 29.88, "altimeterMB": 1013, "altimeterIN": 29.93}, {"timestamp": 1759017600, "validTime": "2025-09-27T21:00:00-03:00", "dateTimeISO": "2025-09-27T21:00:00-03:00", "maxTempC": 13.8, "maxTempF": 57, "minTempC": 13.8, "minTempF": 57, "avgTempC": 13.8, "avgTempF": 57, "tempC": 13.8, "tempF": 57, "wetBulbGlobeTempC": 11.7, "wetBulbGlobeTempF": 53, "maxFeelslikeC": 13.8, "maxFeelslikeF": 57, "minFeelslikeC": 13.8, "minFeelslikeF": 57, "avgFeelslikeC": 13.8, "avgFeelslikeF": 57, "feelslikeC": 13.8, "feelslikeF": 57, "maxDewpointC": 8.4, "maxDewpointF": 47, "minDewpointC": 8.4, "minDewpointF": 47, "avgDewpointC": 8.4, "avgDewpointF": 47, "dewpointC": 8.4, "dewpointF": 47, "maxHumidity": 70, "minHumidity": 70, "humidity": 70, "pop": 0, "precipMM": 0, "precipIN": 0, "iceaccum": null, "iceaccumMM": null, "iceaccumIN": null, "snowCM": 0, "snowIN": 0, "pressureMB": 1015, "pressureIN": 29.97, "windDir": "SW", "windDirDEG": 235, "windSpeedKTS": 12, "windSpeedKPH": 22, "windSpeedMPH": 13, "windSpeedMPS": 6, "windGustKTS": 21, "windGustKPH": 39, "windGustMPH": 25, "windGustMPS": 11, "windDirMax": "SW", "windDirMaxDEG": 235, "windSpeedMaxKTS": 12, "windSpeedMaxKPH": 22, "windSpeedMaxMPH": 13, "windSpeedMaxMPS": 6, "windDirMin": "SW", "windDirMinDEG": 235, "windSpeedMinKTS": 12, "windSpeedMinKPH": 22, "windSpeedMinMPH": 13, "windSpeedMinMPS": 6, "windDir80m": "WSW", "windDir80mDEG": 242, "windSpeed80mKTS": 17, "windSpeed80mKPH": 32, "windSpeed80mMPH": 20, "windSpeed80mMPS": 9, "windGust80mKTS": 17, "windGust80mKPH": 32, "windGust80mMPH": 20, "windGust80mMPS": 9, "windDirMax80m": "WSW", "windDirMax80mDEG": 242, "windSpeedMax80mKTS": 17, "windSpeedMax80mKPH": 32, "windSpeedMax80mMPH": 20, "windSpeedMax80mMPS": 9, "windDirMin80m": "WSW", "windDirMin80mDEG": 242, "windSpeedMin80mKTS": 17, "windSpeedMin80mKPH": 32, "windSpeedMin80mMPH": 20, "windSpeedMin80mMPS": 9, "sky": 30, "cloudsCoded": "FW", "weather": "Mostly Clear", "weatherCoded": [], "weatherPrimary": "Mostly Clear", "weatherPrimaryCoded": "::FW", "icon": "fairn.png", "visibilityKM": 16, "visibilityMI": 9.94, "uvi": 0, "solradWM2": 0, "solradMinWM2": 0, "solradMaxWM2": 0, "isDay": false, "ghi": 0, "solrad": {"azimuthDEG": 248.0116, "zenithDEG": 115.5362, "ghiWM2": 0, "dniWM2": 0, "dhiWM2": 0, "version": "v2"}, "solradClearSkyWM2": 0, "solradClearSkySource": "v2", "maxCoverage": "", "spressureMB": 1013, "spressureIN": 29.91, "altimeterMB": 1015, "altimeterIN": 29.96}], "profile": {"tz": "America/Argentina/Buenos_Aires", "elevM": 17, "elevFT": 56}}]}], "aqi": [{"success": true, "error": null, "response": [{"id": "OPENAQ_2099180", "loc": {"long": -58.682880390221, "lat": -34.881066319298}, "place": {"name": "pontevedra", "state": null, "country": "ar"}, "periods": [{"dateTimeISO": "2025-09-27T03:00:00-03:00", "timestamp": 1758952800, "aqi": 6, "category": "good", "color": "00E400", "method": "airnow", "dominant": "pm10", "health": {"index": null, "category": null, "color": null}, "pollutants": [{"type": "pm10", "name": "particle matter (<10\u00b5m)", "valuePPB": null, "valueUGM3": 6.2846, "aqi": 6, "category": "good", "color": "00E400", "method": "airnow"}]}], "profile": {"tz": "America/Argentina/Buenos_Aires", "sources": [{"name": "AirGradient", "url": null}], "stations": ["OPENAQ_2099180"]}, "relativeTo": {"lat": -34.682473965673, "long": -59.033162742123, "bearing": 125, "bearingENG": "SE", "distanceKM": 38.872, "distanceMI": 24.154}}]}]}